Workbook

Sheet Summary
A1: Arbitrage P&L survey — wallets 0x50dA…4eC1C (Ethereum) and G3yf…f1he (Solana)
A2: All values in USD; stablecoins marked at $1; gas/fees priced at daily Coinbase close. Data through 2026-09-27.
A4: Section | B4: Attempts | C4: Successful | D4: Success rate | E4: Gross gain | F4: Fees + gas | G4: Net P&L
A5: Ethereum atomic flash arbs | B5: =COUNTIFS('ETH arbs'!E:E,"atomic flash arb") -> 242 | C5: =COUNTIFS('ETH arbs'!E:E,"atomic flash arb",'ETH arbs'!D:D,"success") -> 159 | D5: =IF(B5=0,0,C5/B5) -> 0.65702479 | E5: =SUMIFS('ETH arbs'!H:H,'ETH arbs'!E:E,"atomic flash arb") -> 1702.5576 | F5: =SUMIFS('ETH arbs'!I:I,'ETH arbs'!E:E,"atomic flash arb") -> 106.8304 | G5: =E5-F5 -> 1595.7272
A6: Solana atomic flash arbs | B6: =COUNTIFS('SOL arbs'!E:E,"atomic flash arb") -> 1273 | C6: =COUNTIFS('SOL arbs'!E:E,"atomic flash arb",'SOL arbs'!D:D,"success") -> 1156 | D6: =IF(B6=0,0,C6/B6) -> 0.90809112 | E6: =SUMIFS('SOL arbs'!H:H,'SOL arbs'!E:E,"atomic flash arb") -> 844.03639 | F6: =SUMIFS('SOL arbs'!I:I,'SOL arbs'!E:E,"atomic flash arb") -> 2.8048193 | G6: =E6-F6 -> 841.23157
A7: Solana atomic wallet arbs | B7: =COUNTIFS('SOL arbs'!E:E,"atomic wallet arb") -> 71 | C7: =COUNTIFS('SOL arbs'!E:E,"atomic wallet arb",'SOL arbs'!D:D,"success") -> 63 | D7: =IF(B7=0,0,C7/B7) -> 0.88732394 | E7: =SUMIFS('SOL arbs'!H:H,'SOL arbs'!E:E,"atomic wallet arb") -> 147.00654 | F7: =SUMIFS('SOL arbs'!I:I,'SOL arbs'!E:E,"atomic wallet arb") -> 0.079617093 | G7: =E7-F7 -> 146.92692
A8: Solana non-atomic swap legs | B8: =COUNTIFS('SOL non-atomic legs'!E:E,"non-atomic leg") -> 7000 | C8: =COUNTIFS('SOL non-atomic legs'!E:E,"non-atomic leg",'SOL non-atomic legs'!D:D,"success") -> 5030 | D8: =IF(B8=0,0,C8/B8) -> 0.71857143 | E8: =SUMIFS('SOL non-atomic legs'!H:H,'SOL non-atomic legs'!E:E,"non-atomic leg") -> 2873.6892 | F8: =SUMIFS('SOL non-atomic legs'!I:I,'SOL non-atomic legs'!E:E,"non-atomic leg") -> 37.356206 | G8: =E8-F8 -> 2836.333
A9: Atomic arbs total | B9: =SUM(B5:B7) -> 1586 | C9: =SUM(C5:C7) -> 1378 | D9: =IF(B9=0,0,C9/B9) -> 0.86885246 | E9: =SUM(E5:E7) -> 2693.6005 | F9: =SUM(F5:F7) -> 109.71484 | G9: =E9-F9 -> 2583.8857
A10: All bot trading (atomic + non-atomic) | B10: =B9+B8 -> 8586 | C10: =C9+C8 -> 6408 | D10: =IF(B10=0,0,C10/B10) -> 0.74633124 | E10: =E9+E8 -> 5567.2897 | F10: =F9+F8 -> 147.07104 | G10: =E10-F10 -> 5420.2187
A12: Swap provider share (successful atomic arbs, both chains)
A13: Provider | B13: ETH | C13: Solana | D13: Total | E13: Share of trades | F13: Gross gain | G13: Share of gain
A14: 0x | B14: =COUNTIFS('ETH arbs'!F:F,"0x",'ETH arbs'!D:D,"success") -> 159 | C14: =COUNTIFS('SOL arbs'!F:F,"0x",'SOL arbs'!D:D,"success") -> 483 | D14: =B14+C14 -> 642 | E14: =D14/SUM($D$14:$D$17) -> 0.46623094 | F14: =SUMIFS('ETH arbs'!H:H,'ETH arbs'!F:F,"0x")+SUMIFS('SOL arbs'!H:H,'SOL arbs'!F:F,"0x") -> 2087.0764 | G14: =F14/SUM($F$14:$F$17) -> 0.77482773
A15: DFlow | B15: =COUNTIFS('ETH arbs'!F:F,"DFlow",'ETH arbs'!D:D,"success") -> 0 | C15: =COUNTIFS('SOL arbs'!F:F,"DFlow",'SOL arbs'!D:D,"success") -> 534 | D15: =B15+C15 -> 534 | E15: =D15/SUM($D$14:$D$17) -> 0.38779956 | F15: =SUMIFS('ETH arbs'!H:H,'ETH arbs'!F:F,"DFlow")+SUMIFS('SOL arbs'!H:H,'SOL arbs'!F:F,"DFlow") -> 328.50335 | G15: =F15/SUM($F$14:$F$17) -> 0.12195697
A16: OKX | B16: =COUNTIFS('ETH arbs'!F:F,"OKX",'ETH arbs'!D:D,"success") -> 0 | C16: =COUNTIFS('SOL arbs'!F:F,"OKX",'SOL arbs'!D:D,"success") -> 124 | D16: =B16+C16 -> 124 | E16: =D16/SUM($D$14:$D$17) -> 0.090050835 | F16: =SUMIFS('ETH arbs'!H:H,'ETH arbs'!F:F,"OKX")+SUMIFS('SOL arbs'!H:H,'SOL arbs'!F:F,"OKX") -> 111.71385 | G16: =F16/SUM($F$14:$F$17) -> 0.041473801
A17: Jupiter | B17: =COUNTIFS('ETH arbs'!F:F,"Jupiter",'ETH arbs'!D:D,"success") -> 0 | C17: =COUNTIFS('SOL arbs'!F:F,"Jupiter",'SOL arbs'!D:D,"success") -> 77 | D17: =B17+C17 -> 77 | E17: =D17/SUM($D$14:$D$17) -> 0.055918664 | F17: =SUMIFS('ETH arbs'!H:H,'ETH arbs'!F:F,"Jupiter")+SUMIFS('SOL arbs'!H:H,'SOL arbs'!F:F,"Jupiter") -> 166.30695 | G17: =F17/SUM($F$14:$F$17) -> 0.061741504
A19: Provider share incl. non-atomic legs (all successful swaps)
A20: Provider | B20: Swaps | C20: Share
A21: 0x | B21: =COUNTIFS('ETH arbs'!F:F,"0x",'ETH arbs'!D:D,"success")+COUNTIFS('SOL arbs'!F:F,"0x",'SOL arbs'!D:D,"success")+COUNTIFS('SOL non-atomic legs'!F:F,"0x",'SOL non-atomic legs'!D:D,"success") -> 649 | C21: =B21/SUM($B$21:$B$25) -> 0.10129546
A22: DFlow | B22: =COUNTIFS('ETH arbs'!F:F,"DFlow",'ETH arbs'!D:D,"success")+COUNTIFS('SOL arbs'!F:F,"DFlow",'SOL arbs'!D:D,"success")+COUNTIFS('SOL non-atomic legs'!F:F,"DFlow",'SOL non-atomic legs'!D:D,"success") -> 555 | C22: =B22/SUM($B$21:$B$25) -> 0.086624005
A23: OKX | B23: =COUNTIFS('ETH arbs'!F:F,"OKX",'ETH arbs'!D:D,"success")+COUNTIFS('SOL arbs'!F:F,"OKX",'SOL arbs'!D:D,"success")+COUNTIFS('SOL non-atomic legs'!F:F,"OKX",'SOL non-atomic legs'!D:D,"success") -> 737 | C23: =B23/SUM($B$21:$B$25) -> 0.11503044
A24: Jupiter | B24: =COUNTIFS('ETH arbs'!F:F,"Jupiter",'ETH arbs'!D:D,"success")+COUNTIFS('SOL arbs'!F:F,"Jupiter",'SOL arbs'!D:D,"success")+COUNTIFS('SOL non-atomic legs'!F:F,"Jupiter",'SOL non-atomic legs'!D:D,"success") -> 1867 | C24: =B24/SUM($B$21:$B$25) -> 0.29140003
A25: Stable.com | B25: =COUNTIFS('ETH arbs'!F:F,"Stable.com",'ETH arbs'!D:D,"success")+COUNTIFS('SOL arbs'!F:F,"Stable.com",'SOL arbs'!D:D,"success")+COUNTIFS('SOL non-atomic legs'!F:F,"Stable.com",'SOL non-atomic legs'!D:D,"success") -> 2599 | C25: =B25/SUM($B$21:$B$25) -> 0.40565007
A27: Notes
A28: Ethereum: every call from the operator to the 7 executor contracts. Gain = stablecoins entering operator+executors from outside in that tx; reverts cost gas only. All 242 swaps routed through 0x AllowanceHolder -> MainnetSettler.
A29: Solana atomic: flash = txs touching Marginfi account EqRkw9…dLmm; wallet = Stable.com + aggregator in one tx without a flash loan. Gain = wallet stablecoin balance change.
A30: Solana non-atomic legs: separate Stable.com and aggregator swaps (two-token swaps only). Net assumes the inventory round-trips; one-sided cross-chain arrivals/bridge transfers are excluded.
A31: OKX label is for program proVF4…WCqX3u (OKX DEX router, inferred). 4 of 8,751 Solana txs could not be fetched.
A32: Not included: ~31 manual Ethereum wallet swaps (~+$365 net, cross-chain USDG loop legs), LayerZero/bridge fees, Polygon/BSC.

Sheet ETH arbs
A1: chain | B1: time_utc | C1: tx | D1: status | E1: category | F1: provider | G1: detail | H1: stable_gain_usd | I1: fee_usd | J1: net_usd
A2: ethereum | B2: 2026-07-31T15:17:11 | C2: 0xc25fea8375d497419a8f6a2d8ff5644ad6dc647272981a15842a7e74b2ca6292 | D2: reverted | E2: atomic flash arb | F2: 0x | G2: legacy executor 0x4443faee | H2: 0 | I2: 2.9757 | J2: =H2-I2 -> -2.9757
A3: ethereum | B3: 2026-07-31T15:26:23 | C3: 0x98ed57eb1d671108618215c6f5863307a7a88c34d0781dca6db373e1b869fec8 | D3: success | E3: atomic flash arb | F3: 0x | G3: legacy executor 0x4443faee | H3: 61.459859 | I3: 5.1815 | J3: =H3-I3 -> 56.278359
A4: ethereum | B4: 2026-07-31T16:04:11 | C4: 0x37982ed0b7213332df183a1a6d44d36d49bc1c3fc550fa3d2e9ea5c264affa58 | D4: success | E4: atomic flash arb | F4: 0x | G4: legacy executor 0x4443faee | H4: 31.106976 | I4: 3.0085 | J4: =H4-I4 -> 28.098476
A5: ethereum | B5: 2026-07-31T16:24:59 | C5: 0x09ad9e721944acd7d2c43e9da91bc85637518d2228810504d8216be3cb312e41 | D5: success | E5: atomic flash arb | F5: 0x | G5: legacy executor 0xa38d5707 | H5: 38.012488 | I5: 1.4934 | J5: =H5-I5 -> 36.519088
A6: ethereum | B6: 2026-07-31T16:28:23 | C6: 0xfbc79a83165c980e7268c72b3f5fe2527879b5b2a51ac99ab73013f7e018a43e | D6: success | E6: atomic flash arb | F6: 0x | G6: legacy executor 0xa38d5707 | H6: 116.03973 | I6: 1.0395 | J6: =H6-I6 -> 115.00024
A7: ethereum | B7: 2026-07-31T16:28:59 | C7: 0x435eb52c76b824be4a5aa95df5dd7b601b17e76836b8ed36e03a11e29fafa29f | D7: success | E7: atomic flash arb | F7: 0x | G7: legacy executor 0xa38d5707 | H7: 38.347575 | I7: 1.9779 | J7: =H7-I7 -> 36.369675
A8: ethereum | B8: 2026-08-01T01:48:47 | C8: 0x3704878416a0d1ca7881c99241e51b94c4f352576789c6ca374b61444c45222a | D8: success | E8: atomic flash arb | F8: 0x | G8: legacy executor 0xa38d5707 | H8: 20.970772 | I8: 0.0928 | J8: =H8-I8 -> 20.877972
A9: ethereum | B9: 2026-08-14T16:05:59 | C9: 0x2e173daad8005a4e931d8eb8c04ed4ba9a82cb1f4e142e98201e4ed8d1458dd5 | D9: success | E9: atomic flash arb | F9: 0x | G9: legacy executor 0x6fa26637 | H9: 2.641642 | I9: 0.1391 | J9: =H9-I9 -> 2.502542
A10: ethereum | B10: 2026-08-15T17:21:35 | C10: 0xe208c8b0475ea3ace877c7df55f7a1c15e3bed066936aa6f06b28fb177b85fbe | D10: reverted | E10: atomic flash arb | F10: 0x | G10: legacy executor 0xc5ad9f7f | H10: 0 | I10: 0.1889 | J10: =H10-I10 -> -0.1889
A11: ethereum | B11: 2026-08-17T16:22:35 | C11: 0x55d77b243ce3cb20a7a50c01140d9423fb8444cd399e4a6d1a44776e55313459 | D11: reverted | E11: atomic flash arb | F11: 0x | G11: legacy executor 0xc5ad9f7f | H11: 0 | I11: 0.3042 | J11: =H11-I11 -> -0.3042
A12: ethereum | B12: 2026-08-17T16:23:47 | C12: 0xa8edc05a27df3ac0f82fb87a8057e1ecc5fe95ff4b2b607019e4604bb6e67b16 | D12: success | E12: atomic flash arb | F12: 0x | G12: legacy executor 0xc5ad9f7f | H12: 5.998063 | I12: 0.2665 | J12: =H12-I12 -> 5.731563
A13: ethereum | B13: 2026-08-17T19:07:47 | C13: 0xedd6e13f30e0efba7b3a183b13a29f4a69b53d7f25d61ff386b41954bfbf0327 | D13: success | E13: atomic flash arb | F13: 0x | G13: legacy executor 0xc5ad9f7f | H13: 6.745077 | I13: 0.1904 | J13: =H13-I13 -> 6.554677
... A243: ethereum | B243: 2026-09-26T22:42:11 | C243: 0x83d92d625ab541976d490abafa91a2b8a45fd3262db75d93d779ca5c70454db9 | D243: success | E243: atomic flash arb | F243: 0x | G243: PYUSD/USDG Morpho dex-first | H243: 3.846601 | I243: 0.2103 | J243: =H243-I243 -> 3.636301

Sheet SOL arbs
A1: chain | B1: time_utc | C1: tx | D1: status | E1: category | F1: provider | G1: detail | H1: stable_gain_usd | I1: fee_usd | J1: net_usd
A2: solana | B2: 2026-08-01T02:31:01 | C2: 9WcRZqvbzJq4L4L1fQk1xtaY1aDG2oaAReEcn8NDFXMF9gjm8S9pWc3sE6AHGyvbWhjJkUkXQcYvAept7iNtpoU | D2: success | E2: atomic flash arb | F2: none | H2: 0 | I2: 1.2210543 | J2: =H2-I2 -> -1.2210543
A3: solana | B3: 2026-08-01T02:48:26 | C3: BDAHYUR4Umh7eWnKqKcnEU4jr42f7XpK2zx5LvCRMdDJpywcJxEGueY8Scv5xWTstURLY8tbpSA6HYRnUCNs9f6 | D3: success | E3: atomic flash arb | F3: Jupiter | G3: USDT +10.0077, USDC +27.9883 | H3: 37.996 | I3: 0.0006997518 | J3: =H3-I3 -> 37.9953
A4: solana | B4: 2026-08-01T03:01:09 | C4: 34f64CexjEZzw6fBZT9iPxRbbkHiJY6KFuxQMe4mTLc73W7UimrB3xMVMnyJPKy4uEizAet2mmzZ5wfr6oV2NB4V | D4: success | E4: atomic flash arb | F4: Jupiter | G4: USDT +4.9012, USDC +11.8396 | H4: 16.740892 | I4: 0.00068695716 | J4: =H4-I4 -> 16.740205
A5: solana | B5: 2026-08-13T10:33:26 | C5: 2VDEgMx1775c4mp5xErpLzUiJzV1xbACXF5n2gU1gNKBUbnL1M7rZWkoSV2HaEaQtyjiD2x1KApP3n191HWe1iSe | D5: success | E5: atomic flash arb | F5: Jupiter | G5: USDC +0.2288 | H5: 0.228797 | I5: 0.00074327613 | J5: =H5-I5 -> 0.22805372
A6: solana | B6: 2026-08-21T09:46:23 | C6: 5PJfBRgTcTzzjNRt9Z7fa1fi6guMMZyfPNqiZXFpWMpuwJUoUJM4jvkUydkZPAsQFDHA8vm4LBumeacJpwTgv4p6 | D6: failed | E6: atomic flash arb | F6: Jupiter | H6: 0 | I6: 0.00094244832 | J6: =H6-I6 -> -0.00094244832
A7: solana | B7: 2026-08-21T09:47:17 | C7: 2UMgq3TLDaQSQ2MUoTmnwjehvD2NeW3W1iEcQQhX3BX8eDR9oi3k9FSpepUE83vRHYXzYoHuhNN8eL8ipTfjATjQ | D7: success | E7: atomic flash arb | F7: Jupiter | G7: PYUSD +1.3644 | H7: 1.364443 | I7: 0.00094244832 | J7: =H7-I7 -> 1.3635006
A8: solana | B8: 2026-08-21T09:49:32 | C8: 4nwRWJPbecGKK4HjWLGBMnWhvTD8PaMAm8oRsdYcjz8HfZq8FaPkcxbav354JMxNfbpx7cjhpMuoSGbG2KZutpmy | D8: success | E8: atomic flash arb | F8: Jupiter | G8: PYUSD +1.2659 | H8: 1.265888 | I8: 0.00094347924 | J8: =H8-I8 -> 1.2649445
A9: solana | B9: 2026-08-21T09:52:09 | C9: 2q91x3sJxrCPcAk9r5wJztguJgReX2WbEvRzDjV1zkpbtXBemc7WSezxEJERvs8XD5DSJMFaFcMzWE7yMebMdY6r | D9: success | E9: atomic flash arb | F9: Jupiter | G9: PYUSD +1.1650 | H9: 1.164965 | I9: 0.00094479132 | J9: =H9-I9 -> 1.1640202
A10: solana | B10: 2026-08-21T10:03:54 | C10: FYz2Bsdh48TYuC4t6rwKZsGboUwSqsxkyjJTn6sk4KhzriX9mQKV81tC6vEXaADvASy4QR8PPs2fXJNDNk5ogTL | D10: success | E10: atomic flash arb | F10: Jupiter | G10: PYUSD +2.0822 | H10: 2.082231 | I10: 0.00095041452 | J10: =H10-I10 -> 2.0812806
A11: solana | B11: 2026-08-21T10:04:52 | C11: 472PXUj4RyNEcREwRbbmZJRTiK4mjFaNNNS4C24TbKpmhqADsv6g5Tx3JLfabYoNCvgKwFpoGLfRhhcofi7ExMHv | D11: success | E11: atomic flash arb | F11: Jupiter | G11: PYUSD +1.5452 | H11: 1.545188 | I11: 0.00095153916 | J11: =H11-I11 -> 1.5442365
A12: solana | B12: 2026-08-21T10:05:56 | C12: 2LSKSBczUGzJn5gd7dzziYu4CZGEgBevWrQFgLYCxRNwBdge5pZNf6Thm8RSEHWEVXGZMFd3GxuzzS4RpSP1gNBs | D12: success | E12: atomic flash arb | F12: Jupiter | G12: PYUSD +1.3852 | H12: 1.385181 | I12: 0.00095285124 | J12: =H12-I12 -> 1.3842281
A13: solana | B13: 2026-08-22T11:01:47 | C13: 5BHHoHFQqNxWc1P4ghGKHN7Tox7eX9nAgY8GyArJ8jBqwPekZPjkVt31vCNpJKXpJzCN9wbtAWoP36V6SbWxXQp | D13: success | E13: atomic flash arb | F13: Jupiter | G13: USDC +1.2528 | H13: 1.252837 | I13: 0.00087918746 | J13: =H13-I13 -> 1.2519578
A14: solana | B14: 2026-08-24T08:47:12 | C14: 5uaD7ft2t4BhikXhXpCokcPTpDtAU8ah74hsCF24vSYjwCVz9HBHART8Ab5aoNeJYaSReZyjP7zfyjExyfY3K6eU | D14: success | E14: atomic flash arb | F14: Jupiter | G14: PYUSD +0.8121 | H14: 0.812115 | I14: 0.00097505244 | J14: =H14-I14 -> 0.81113995
A15: solana | B15: 2026-08-24T08:51:07 | C15: 2aN7orRG1J8v7FJhkwUD7FfEuJzT8mUVcJNZqwWKCg9E8bw6272E8hmW1XkkoWGP2fqxV3fHAYDsg3j7xCzV3Soe | D15: success | E15: atomic flash arb | F15: Jupiter | G15: PYUSD +0.8533 | H15: 0.853309 | I15: 0.00098336592 | J15: =H15-I15 -> 0.85232563
A16: solana | B16: 2026-08-24T08:51:30 | C16: 3Se152jVgfqdR7p7MGPCk6DhEc1DntAk3P9bUHdHuRcNPa9wjd2vmTRjVjjkUXmG5BKfdG2b4RMy3DJgqgDyijzN | D16: success | E16: atomic flash arb | F16: Jupiter | G16: PYUSD +0.7334 | H16: 0.733389 | I16: 0.00098524635 | J16: =H16-I16 -> 0.73240375
A17: solana | B17: 2026-08-24T08:51:49 | C17: 5AXuqy93ih87ta92m89L2MnXqkjwhA6cuaSYj3ZAhCnnALjx3NXTRaYoTESHP1rf4JVa7H53TcbvENEbxgrgpzFv | D17: success | E17: atomic flash arb | F17: Jupiter | G17: PYUSD +0.6807 | H17: 0.680675 | I17: 0.0009857412 | J17: =H17-I17 -> 0.67968926
A18: solana | B18: 2026-08-24T08:52:13 | C18: 3cikqzAXhqJnL51vDBm8znaNDcJBaa2QhqXo1ueqRmDRNCARRKtnNKbb73bFRjoDMP3PZGMDTtDJkSDkqqzvBHnK | D18: success | E18: atomic flash arb | F18: Jupiter | G18: PYUSD +0.8749 | H18: 0.874949 | I18: 0.00097911021 | J18: =H18-I18 -> 0.87396989
... A25: solana | B25: 2026-08-25T09:06:29 | C25: 4YZ6KL8vEVHCn1quHKNjep1kucUfTLS79vH4VfuQUB5DoEXLztfoZbPGWCrpUyA2NFKj6DtW4EQFycCXJbSNUsNG | D25: success | E25: atomic flash arb | F25: Jupiter | G25: PYUSD +1.6717 | H25: 1.671739 | I25: 0.0011115577 | J25: =H25-I25 -> 1.6706274
A26: solana | B26: 2026-08-30T22:26:37 | C26: 3NrUvaL15mntLAmetubLsMAUEax9ygzapDyTBcW7TC75QJuC2kUH9FbTE5CxEbJeJ8a5tgdmyQkMnU1eKmPaR4v8 | D26: failed | E26: atomic flash arb | F26: Jupiter | H26: 0 | I26: 0.0010503653 | J26: =H26-I26 -> -0.0010503653
A27: solana | B27: 2026-08-30T22:55:49 | C27: 5Cs45CRc93YDbm1AiTrw4Pi4oceciZsmVNE5LR8WaGvC4du2RzMXsoiL8mAqcTH4G1Cpt1mMtrx2oC9yoFLPcU5W | D27: success | E27: atomic flash arb | F27: Jupiter | G27: PYUSD +6.3869 | H27: 6.386879 | I27: 0.001025233 | J27: =H27-I27 -> 6.3858538
A28: solana | B28: 2026-08-30T23:07:38 | C28: 2Vdee9JyS5tERx93WBTP9Xoa7WBTB7Q4DD1iV8JW2mQ3oEvGeDC13MRDse9nNU8LwNqqdFWsRqRLdfMCgdbcL4HT | D28: success | E28: atomic flash arb | F28: Jupiter | G28: PYUSD +0.4991 | H28: 0.499099 | I28: 0.0010042725 | J28: =H28-I28 -> 0.49809473
A29: solana | B29: 2026-08-30T23:08:53 | C29: 43gP3ptrroes4e5FjimSAku4BUZvbHUFcpQCJ864zJviEznYrWuS5PG9VUGzPLgPf8XN2113drYZmq5P2oWe4KRh | D29: success | E29: atomic flash arb | F29: Jupiter | G29: PYUSD +6.1347 | H29: 6.134734 | I29: 0.0010259452 | J29: =H29-I29 -> 6.1337081
A30: solana | B30: 2026-08-30T23:11:59 | C30: 2wXRVfbpyLPh5P6kqdr65U9ZX1axjhGWS934xhJ9Wi1cqy4ZByaZcKxDDdzEo1PAQv7H7y2BJ6expGGBku8K4WZu | D30: success | E30: atomic flash arb | F30: Jupiter | G30: PYUSD +5.6987 | H30: 5.698691 | I30: 0.001032559 | J30: =H30-I30 -> 5.6976584
A31: solana | B31: 2026-08-30T23:25:27 | C31: 4GSxq7dJiLeFAypm6EsKMLNQA6NqanbGsN7Br7Ze4Q1ZSj1YAjvwC5NA68oQC6xjPdHTDrfPJs5kJ8pRa1Fmu7mR | D31: success | E31: atomic flash arb | F31: Jupiter | G31: PYUSD +4.6382 | H31: 4.638247 | I31: 0.0010452778 | J31: =H31-I31 -> 4.6372017
A32: solana | B32: 2026-08-30T23:34:13 | C32: 3Ui9hKvApKfarG21QhbRnCi3KjLVzykgqvdXRXn6GCWogmp8n6hCX2m6YwXm8VQZFrZ6pcb9ciVGGf6q51TMuPQS | D32: success | E32: atomic flash arb | F32: Jupiter | G32: PYUSD +0.8809 | H32: 0.880893 | I32: 0.0010099705 | J32: =H32-I32 -> 0.87988303
A33: solana | B33: 2026-08-31T00:03:43 | C33: 3njy2ZrVBPrnY61nsoCK46nuQddKgmTZZdJw19b6oWvAuD8W8v11xpm7dgHzPAhcZrxSvVmMRyX1crKzENFFL9xY | D33: success | E33: atomic flash arb | F33: Jupiter | G33: PYUSD +3.2262 | H33: 3.226209 | I33: 0.0010385402 | J33: =H33-I33 -> 3.2251705
A34: solana | B34: 2026-08-31T00:19:17 | C34: 2WY4aZwK6VdjRwDNV9gRVJiqrAR5WGvp3bnhdxxfpcduZLtqpWAGw9phxHWijQYZCBz7WPmtXiGxa1ty9bNQgJ7b | D34: success | E34: atomic flash arb | F34: Jupiter | G34: PYUSD +3.3836 | H34: 3.383589 | I34: 0.0010385402 | J34: =H34-I34 -> 3.3825505
A35: solana | B35: 2026-08-31T00:20:33 | C35: 3xPzAmmcs5kCmd3oeyPb7cF8uQ3GUNAkatUPtFzPq8xcfY6qX3KDMnLJvJh8vX6gPoFE4GXFhwFNgSeHrNp99aaE | D35: success | E35: atomic flash arb | F35: Jupiter | G35: PYUSD +1.1800 | H35: 1.18002 | I35: 0.0010395706 | J35: =H35-I35 -> 1.1789804
A36: solana | B36: 2026-08-31T00:26:10 | C36: ZDH2gP8FCP1Ssuqcir6g6VDLDg29Ewp3QJk4AuCq1b928KqxptwZjyY1pEEf16ZjNVm8n9xAi9X3Gztfm8nTFbb | D36: success | E36: atomic flash arb | F36: Jupiter | G36: PYUSD +3.0482 | H36: 3.048191 | I36: 0.0010388493 | J36: =H36-I36 -> 3.0471522
A37: solana | B37: 2026-08-31T00:28:51 | C37: 5imZktXZ5Kn4N6kYJGuZ4UnC3UcCUqAtuAzug9EmkSQtmtzffemHD25XEH4aZBk8EKvtKLZS1o7NdbdLVa7zSu6R | D37: success | E37: atomic flash arb | F37: Jupiter | G37: PYUSD +2.7977 | H37: 2.79771 | I37: 0.0010582208 | J37: =H37-I37 -> 2.7966518
A38: solana | B38: 2026-08-31T00:39:11 | C38: Ha9w1o2Wt5phJXGkTgMbDgzNq87cXamad6Pmwht2cyMju5vZNr7uBooFkrU28moxsj48rqYbNyUvy9uXVkZ4iJP | D38: success | E38: atomic flash arb | F38: Jupiter | G38: PYUSD +2.6238 | H38: 2.623799 | I38: 0.0010388493 | J38: =H38-I38 -> 2.6227602
... A77: solana | B77: 2026-09-03T11:07:25 | C77: 3kNdnmFg8g4AB9X19aRP63YXSTGo8LmJESjXTmmo6c6mbwGNgH9Ka3ifV5QM7C97hb4muszh2uFAaseDeRqS84eD | D77: success | E77: atomic wallet arb | F77: 0x | G77: PYUSD +1.8430 | H77: 1.843013 | I77: 0.0009526101 | J77: =H77-I77 -> 1.8420604
A78: solana | B78: 2026-09-03T12:31:51 | C78: w4BF4gaWF26jF3dyZYMCeyxymWMH3acgkju4AcitRZdub3minnubeJi6E6YTtHWxxL8rM5igXEMwd8zrjZBqLFE | D78: failed | E78: atomic wallet arb | F78: 0x | H78: 0 | I78: 0.0010433497 | J78: =H78-I78 -> -0.0010433497
A79: solana | B79: 2026-09-03T12:32:33 | C79: 36T53fDqS1RsT5eYbZ14BqvQoUwXFTzVnxmoRCGpZa8Uw9YKMpvtudWZvpqF7iJ3mVuWi84zmbAtMLV96q68Hzsg | D79: success | E79: atomic wallet arb | F79: 0x | G79: PYUSD +1.7738 | H79: 1.773831 | I79: 0.0010355542 | J79: =H79-I79 -> 1.7727954
A80: solana | B80: 2026-09-03T12:34:42 | C80: 3BCsHArjntQNGo4k27hbUKPRCVMUcryanboPk2kR2BSfMRLuNo5smUn1fVQcs1hzBMdSRgJoGeA1eckeGY3rTCXE | D80: success | E80: atomic wallet arb | F80: 0x | G80: PYUSD +2.2127 | H80: 2.21273 | I80: 0.0010057234 | J80: =H80-I80 -> 2.2117243
A81: solana | B81: 2026-09-03T12:49:09 | C81: 575F82LAVZfRwFGgQ9crXTdimDXX6z8PFQLVRcANETmV8DCKEX1Piq8NPXwGrk123Ro549x92nEEUaU9ZaC6bwMb | D81: success | E81: atomic wallet arb | F81: 0x | G81: PYUSD +1.1950 | H81: 1.194973 | I81: 0.0010373212 | J81: =H81-I81 -> 1.1939357
A82: solana | B82: 2026-09-03T18:09:49 | C82: 2Vzj7arTHHuxSsFerrwHpEjV7kbDpnZBnM27E6ouoe1PQU74bHiUFT1jafXvZv8NdnfZ9bV2kLLPU6j2zEqGqpdN | D82: success | E82: atomic wallet arb | F82: 0x | G82: PYUSD +5.8775 | H82: 5.87748 | I82: 0.001022146 | J82: =H82-I82 -> 5.8764579
A83: solana | B83: 2026-09-03T18:10:42 | C83: 5fJnfyryXH87Zcb4R8wV7itpEqRieLKAkUs1z9dkHzsbtKpy2iRECg4UStfhtV26NJyxr5bGz16sVo6WE2wRANp3 | D83: success | E83: atomic wallet arb | F83: 0x | G83: PYUSD +6.7094 | H83: 6.709401 | I83: 0.001009985 | J83: =H83-I83 -> 6.708391
A84: solana | B84: 2026-09-03T18:13:18 | C84: 2Ln7tAWEV5uNnE3zz5Lkey66sDoJuXt4FRmwLpYFvp1AZMicpDrhgHQAgAZU5qXeZyAWXamKqPo4npfYbipRgdWo | D84: success | E84: atomic wallet arb | F84: 0x | G84: PYUSD +2.6133 | H84: 2.613336 | I84: 0.00099231518 | J84: =H84-I84 -> 2.6123437
A85: solana | B85: 2026-09-04T01:25:45 | C85: 5mMFXL3q4KBBM5YwYtgVudLw6n5X3QPSwAk94R8zNnA4gwLwoiqnFgzYfqcQtRm4qm7kQJ7BJ6AWGME64xw5sSx2 | D85: success | E85: atomic wallet arb | F85: 0x | G85: PYUSD +4.0581 | H85: 4.058126 | I85: 0.0010938216 | J85: =H85-I85 -> 4.0570322
A86: solana | B86: 2026-09-04T01:31:58 | C86: 4tDw6HKqVwCRquNHPcjLuomtYKGSLyUr8rrPYDkcTta6mhg28YpxD9PiKiahQ4JGjjBdE58udkYc5pzkv31gWoaP | D86: success | E86: atomic wallet arb | F86: 0x | G86: PYUSD +3.6471 | H86: 3.647102 | I86: 0.0010760822 | J86: =H86-I86 -> 3.6460259
A87: solana | B87: 2026-09-04T01:38:28 | C87: 5tFRvqE6CAQtzwUqeGsW6CXXVq5hKCPVc1pMFZcnQLiypPJ82iBfA4aZLq2fkcEFZc4jkND6CXcZ6wyDz2WRfET5 | D87: success | E87: atomic wallet arb | F87: 0x | G87: PYUSD +1.8913 | H87: 1.891303 | I87: 0.00093702245 | J87: =H87-I87 -> 1.890366
A88: solana | B88: 2026-09-04T06:09:38 | C88: 2oUKCxTx1ijov2hLmYVD9bCir6n8AsGPVexQaXsSzhxWRet3eWTDY34yo55JWKhRsEZRkxnf2PvYZ92KUbCgBgMW | D88: success | E88: atomic wallet arb | F88: 0x | G88: PYUSD +4.6700 | H88: 4.670006 | I88: 0.0010593625 | J88: =H88-I88 -> 4.6689466
A89: solana | B89: 2026-09-04T06:11:43 | C89: 59R5gkVFf2EMfV3FrU6B5vaR5LGspxBoxgJ4CX9jzpWxPoorPMv5Ri9d1RT1m5UQDwtcJGfzcSPGUejsWCpmiR4t | D89: failed | E89: atomic wallet arb | F89: 0x | H89: 0 | I89: 0.001037953 | J89: =H89-I89 -> -0.001037953
A90: solana | B90: 2026-09-04T06:12:26 | C90: 5KKBqV4XPgEh8ZVXBeYUNfEsYH2qsy85htZdbuS5ytbCvfL62zynobuV9gbVkXaD3atFJGEkKQYims3rPQR3fGhK | D90: success | E90: atomic wallet arb | F90: 0x | G90: PYUSD +2.0078 | H90: 2.007791 | I90: 0.001005227 | J90: =H90-I90 -> 2.0067858
A91: solana | B91: 2026-09-04T06:17:45 | C91: 3Robu7H5EwXf4KTVeMMjaqBowPqcPHkqSkoE55tYetwWkfDsgEToZmBngDVTRJiX1k3Bxc76V9CQYFnFiZ48ZA9a | D91: success | E91: atomic wallet arb | F91: 0x | G91: PYUSD +1.3987 | H91: 1.398725 | I91: 0.0009579222 | J91: =H91-I91 -> 1.3977671
A92: solana | B92: 2026-09-04T12:10:31 | C92: DyHSD28Yd1P7RzQYjFCsU4qHaVkjoCaPgnyMStykoGeUdEfZVygW6txgsYcH6EGXFmF67acL5ZxPKcEzQMYFgy2 | D92: success | E92: atomic wallet arb | F92: 0x | G92: PYUSD +2.6618 | H92: 2.661806 | I92: 0.0010135869 | J92: =H92-I92 -> 2.6607924
A93: solana | B93: 2026-09-04T12:37:27 | C93: 4vCkqDiZFwdgAaBxMjqbZt23RfJB7XMZ3Jj8sPmsnTajjtssfhtyfvmJgkf3xkvSkxDHWLN2djKtshQS1joQZBbu | D93: success | E93: atomic wallet arb | F93: 0x | G93: PYUSD +1.7504 | H93: 1.750378 | I93: 0.0010581391 | J93: =H93-I93 -> 1.7493199
A94: solana | B94: 2026-09-04T14:05:11 | C94: 5gHmsF1Q6pKT1wthjRXoZgPqMk4B1mgpvcfSSgbTMhWn23VaAGkc3fkgdhuAGWfcxEyqZUdhvfGNSbbd8vP7oLL1 | D94: success | E94: atomic wallet arb | F94: 0x | G94: PYUSD +1.3820 | H94: 1.382047 | I94: 0.00095435395 | J94: =H94-I94 -> 1.3810926
A95: solana | B95: 2026-09-04T15:04:42 | C95: 3DQG8SKx1Vz5BsZCyCnfKyEnsLML6hZzStjYJQ8yuCLYPChxccDfaEDRV5fYurmm1SuZt4qdNeayRCpUnSgnHxbo | D95: success | E95: atomic wallet arb | F95: OKX | G95: PYUSD +1.0349 | H95: 1.034907 | I95: 0.00092376895 | J95: =H95-I95 -> 1.0339832
A96: solana | B96: 2026-09-04T15:05:18 | C96: 2u4r2rXffhrEcuCFFJXFm9pS9Ba3UWFxfWYW1qNvkSJpKoQsDDfFLiHaFiM4MXoNBAZzKNPuRQc9P9hva2HLxGsN | D96: failed | E96: atomic wallet arb | F96: OKX | H96: 0 | I96: 0.0009834097 | J96: =H96-I96 -> -0.0009834097
A97: solana | B97: 2026-09-04T15:05:57 | C97: 3QURHNLhFDBY3mLdKgeNuE7SVqXkBJTHjEX6LMeJsMRhY3Xi8RQDRUVabqrTKJFxCziEXFwTqx3LNyBd8fNuU7tB | D97: success | E97: atomic wallet arb | F97: OKX | G97: PYUSD +1.2421 | H97: 1.242121 | I97: 0.0009373283 | J97: =H97-I97 -> 1.2411837
A98: solana | B98: 2026-09-04T15:43:28 | C98: 4sUyHrsqFU6UQBAjEbewUPLRVpyDahjsTs5CU8TV5kKdhiMZhwhBaJNLNmRdwGu1fGzznMx7vfn9zWed7eDyF4rP | D98: success | E98: atomic wallet arb | F98: OKX | G98: PYUSD +1.4944 | H98: 1.494412 | I98: 0.00099533785 | J98: =H98-I98 -> 1.4934167
A99: solana | B99: 2026-09-04T16:04:04 | C99: 38SZriuaytirnEsSoRRS2GRarBULcJEQdCM7j4qjKSd41xHZyeHAPBkxRVkinCUmqH4p2MsnvzW9iGwopDUEj3gm | D99: success | E99: atomic wallet arb | F99: 0x | G99: PYUSD +1.0440 | H99: 1.044046 | I99: 0.0010564059 | J99: =H99-I99 -> 1.0429896
A100: solana | B100: 2026-09-05T06:34:15 | C100: 4pRkH1M5Z9rW6P7JQKyz86Dk1VP39yk17CKLK9uNrAgJJj7NvP8FoxUgrJz1Ca2C8tawxFL8CeyWhMkL1FzfWsqP | D100: success | E100: atomic flash arb | F100: OKX | G100: PYUSD +4.6535 | H100: 4.653455 | I100: 0.0011396231 | J100: =H100-I100 -> 4.6523154
A101: solana | B101: 2026-09-05T18:11:07 | C101: 5NearxAu2mNQc36MhHQ5eA9JBoeVt4XRFX5pKxtbfvSfg7saGQ4Zui84kn37BijiiJe5fMQ7M9wPcVEvxcyGLQRw | D101: failed | E101: atomic wallet arb | F101: OKX | H101: 0 | I101: 0.0012766461 | J101: =H101-I101 -> -0.0012766461
A102: solana | B102: 2026-09-05T18:11:50 | C102: 4wf7CZT3xuwBczMTUej95GLhpruabXQtcoHSWDQG1t4wdct8xyUaaKkW68yh2WjSrUvyUY8ccdzEYtWpn8QVQVPg | D102: success | E102: atomic wallet arb | F102: OKX | G102: PYUSD +2.4385 | H102: 2.43855 | I102: 0.0011187807 | J102: =H102-I102 -> 2.4374312
A103: solana | B103: 2026-09-05T18:12:45 | C103: 7AB4NVC6GSRY7pacYaNyQmJZzqLSm1ntGWUvJEJLq99Vu2rH5Ripoaa19ktwz2Xx2EZPgvzXMQndtxD4S55aYmL | D103: failed | E103: atomic wallet arb | F103: OKX | H103: 0 | I103: 0.0010099258 | J103: =H103-I103 -> -0.0010099258
A104: solana | B104: 2026-09-05T18:13:32 | C104: 5m4AnxtDfLscC5pgHy1AYe5JhjoEUZUjhyoa292ytR1Eg1rbnW5yQ5LK6zkVCqZefpGKq8dxE93AJn8GHCfQ1jd | D104: success | E104: atomic wallet arb | F104: OKX | G104: PYUSD +2.3398 | H104: 2.339793 | I104: 0.0011657276 | J104: =H104-I104 -> 2.3386273
A105: solana | B105: 2026-09-06T00:11:12 | C105: WFwcb3ANhAR6UpRYVDYpVxmHPWXGi5QR6StyR81w6mYH9HzKpa2qbBjbhuSRu3WJ4bBgAUN61Zr6ruP6F1dr8vV | D105: success | E105: atomic wallet arb | F105: 0x | G105: PYUSD +4.5363 | H105: 4.536271 | I105: 0.0013646074 | J105: =H105-I105 -> 4.5349064
A106: solana | B106: 2026-09-06T00:11:59 | C106: 2E1Gyo96zQD2HQJfLE8ub6CnvY45Zn4A6P2meM7VD4YX4WH279zhcN6Aoyn4eNmH8UTHGFyxAVUei8wzTbFLzDTT | D106: success | E106: atomic wallet arb | F106: 0x | G106: PYUSD +4.5467 | H106: 4.546726 | I106: 0.0013515005 | J106: =H106-I106 -> 4.5453745
A107: solana | B107: 2026-09-06T02:19:29 | C107: 2ch8aBjpUddxDXugpZXr1k8wqsEkMVHtk5NR5XrNQbcZ5JRB7zkvSbHwDBDrfHHMAwHX1dffTre6SEjNLRSWzeqT | D107: success | E107: atomic wallet arb | F107: OKX | G107: PYUSD +1.1226 | H107: 1.122608 | I107: 0.00098983584 | J107: =H107-I107 -> 1.1216182
A108: solana | B108: 2026-09-06T02:21:35 | C108: 3EwjJUxguM2qk7j4vWqBuqfe5MDDzKcmaaSTnTM32XYdB2QBVMfAKmkCDPRtp2wsXiFTdAJ4Yz7waQ66feekyRkS | D108: success | E108: atomic wallet arb | F108: OKX | G108: PYUSD +5.6687 | H108: 5.668655 | I108: 0.0011777011 | J108: =H108-I108 -> 5.6674773
A109: solana | B109: 2026-09-06T02:36:27 | C109: 2ttXwXaLYHNCpMNBxq1nATTDxji1oWkFVijF3Bk1YLkNz2yAUJTKCF3xmdtt9DM5VRoWN3u8mHP7cbUXcQFvM8tE | D109: success | E109: atomic wallet arb | F109: OKX | G109: PYUSD +1.0982 | H109: 1.098243 | I109: 0.0012288499 | J109: =H109-I109 -> 1.0970142
A110: solana | B110: 2026-09-06T02:40:02 | C110: 5zVseDYknQNPpXeczh3jCdXUZvaBZUMPpdFdK1vcG3PakZRpGXTmYu4mBU9b2fxQwwxEeHynZpV5dsTheNcxzjUA | D110: success | E110: atomic wallet arb | F110: OKX | G110: PYUSD +1.0086 | H110: 1.008562 | I110: 0.0011718403 | J110: =H110-I110 -> 1.0073902
A111: solana | B111: 2026-09-06T04:02:14 | C111: 33RUqpaL8Ys9rv6eT4K9RMSHiVS1Kzx7sSPSLW4zkqui6C6c3bPKwtK2oLVqPYEe4WZkczyjs6uTsXy6s2jBnVNk | D111: success | E111: atomic wallet arb | F111: 0x | G111: PYUSD +1.1113 | H111: 1.111294 | I111: 0.0012110544 | J111: =H111-I111 -> 1.1100829
A112: solana | B112: 2026-09-06T04:43:44 | C112: 4sT5fHbQasfSfnfmNeR2xrRAFjTtekx7Mv8qJeyNYuxcL1JApPndoX2X2uNQw8nYxnUpVVq6XQznpfXj6BnFLXX7 | D112: success | E112: atomic wallet arb | F112: 0x | G112: PYUSD +1.0806 | H112: 1.080592 | I112: 0.0012489898 | J112: =H112-I112 -> 1.079343
A113: solana | B113: 2026-09-06T04:44:23 | C113: 37P56Tp94Hju91uZNkTEquxtwkuCLzEmakBQ8JhW78ttxFbwJWBqprxCw3ZigMM2u2pvyyGpYyNQRxZq9rtPwR8b | D113: success | E113: atomic wallet arb | F113: 0x | G113: PYUSD +1.5058 | H113: 1.50584 | I113: 0.0011872915 | J113: =H113-I113 -> 1.5046527
A114: solana | B114: 2026-09-06T04:52:11 | C114: 28AsfuECKPGq47GBydNovG5GnKp5QNNUYj2AkAtxJfRk7QiDdLkUmNy45xmYZWNrxwNAGLWJPvQP2u23raRXiFPF | D114: failed | E114: atomic wallet arb | F114: 0x | H114: 0 | I114: 0.0011146176 | J114: =H114-I114 -> -0.0011146176
A115: solana | B115: 2026-09-06T05:56:17 | C115: 3AuuTsiZLwi3GRg4XpBATMo6TZdeV1D7eayjZQD1Pnpxx4ztzn4XtmcQh85uxMkzNrLfo82Y94bjDvhEx77p5YBW | D115: success | E115: atomic wallet arb | F115: 0x | G115: PYUSD +1.0435 | H115: 1.043475 | I115: 0.001027345 | J115: =H115-I115 -> 1.0424477
A116: solana | B116: 2026-09-06T06:07:33 | C116: 2uqAki9JMxmLD37XkjBC5e9aCPR5m9rZoMReqGBPG1QmE9iBocVTD63zyvHWXGSKNTmvFp48AWqYnhf8zMGUmQV7 | D116: success | E116: atomic wallet arb | F116: OKX | G116: PYUSD +2.0383 | H116: 2.038268 | I116: 0.0012432355 | J116: =H116-I116 -> 2.0370248
A117: solana | B117: 2026-09-06T06:08:16 | C117: uT1xHHHVrzEHZ9bvcjcEw24cXFaLVx5qkxKCD93FWo7f9nC5N78zcyd2rBNR2dZmikMhGdDNTGfsKucckb3JE9c | D117: success | E117: atomic wallet arb | F117: OKX | G117: PYUSD +1.2472 | H117: 1.247241 | I117: 0.0012485635 | J117: =H117-I117 -> 1.2459924
A118: solana | B118: 2026-09-06T07:21:45 | C118: 4dZFzJsAzx5ytj8S7vaqE7jDPom7xCcjpeTACW82ziycySvDA7jQexeia4M8CPdCAeeHPBv9myALLRwPoA9ULrQE | D118: failed | E118: atomic wallet arb | F118: OKX | H118: 0 | I118: 0.0012468586 | J118: =H118-I118 -> -0.0012468586
A119: solana | B119: 2026-09-06T07:22:54 | C119: 3L42o7f3PNSZUnxWBw3koqqKKiqAdchK8noWsES4GNK4MidUvjdUkwgkoGTrNPGVvEYUEjjmKYWQaUBTnLKQdvzK | D119: success | E119: atomic wallet arb | F119: 0x | G119: PYUSD +1.0411 | H119: 1.04108 | I119: 0.0012145709 | J119: =H119-I119 -> 1.0398654
A120: solana | B120: 2026-09-06T08:53:02 | C120: 4Tshmv8ch4UFmZqXGkh3Rad2KCDVC9AwqUm2qg9u2QKgTmhaovkcuMy6CaAK42FgpiJftRdFbMU78K4gJhe8kW1i | D120: success | E120: atomic wallet arb | F120: 0x | G120: PYUSD +1.7705 | H120: 1.770453 | I120: 0.0011972016 | J120: =H120-I120 -> 1.7692558
A121: solana | B121: 2026-09-06T08:55:23 | C121: 2Hxsky1En3149QDafbox4VhixqCQdgu6m5aR6iLCBxQJvdqXHeB2vUg28Ah2Wz6GuHiCm7PXZGY78KNhwWFWd888 | D121: success | E121: atomic wallet arb | F121: 0x | G121: PYUSD +1.1745 | H121: 1.174495 | I121: 0.0011609712 | J121: =H121-I121 -> 1.173334
A122: solana | B122: 2026-09-06T11:20:07 | C122: 4hTBUAfDQzaYhe6tUyTbJrLxC7gY1hd4qeKhaTBdNZBJgfmvW2Rjgn9VBphTC7AWmmUKM9UAUaA3Y3FygDNybVjc | D122: success | E122: atomic wallet arb | F122: 0x | G122: PYUSD +1.1620 | H122: 1.162043 | I122: 0.0012700886 | J122: =H122-I122 -> 1.1607729
A123: solana | B123: 2026-09-06T12:57:43 | C123: 2KfZZyA9eiDPgW7TDX5KmWxf7hh8VMHvr1fy3bApN9nKX2sUHgtdw5PxCVzfGco5pjZxw9xukvB7mTpH3nyt1HwM | D123: success | E123: atomic wallet arb | F123: 0x | G123: PYUSD +2.5889 | H123: 2.588863 | I123: 0.0011965622 | J123: =H123-I123 -> 2.5876664
A124: solana | B124: 2026-09-06T12:58:33 | C124: STUWSGfH63FUXSHRS1VvmNSZRD5muK8gMYsU1zVasQWioxHDHtiPuHFPr4VQZw1gC7D14h1d96TLex9up7zB6Wi | D124: failed | E124: atomic wallet arb | F124: 0x | H124: 0 | I124: 0.0012729658 | J124: =H124-I124 -> -0.0012729658
A125: solana | B125: 2026-09-06T13:12:00 | C125: 1cH2dtuZo3F5yL6GeEtg1DGF24LKMHGw35csPVhVrA6YRChN9xSt9zUEFmjeWJYcJbinmHEvkVTCEAUGQBndxFr | D125: success | E125: atomic wallet arb | F125: 0x | G125: PYUSD +1.0284 | H125: 1.028396 | I125: 0.0012728592 | J125: =H125-I125 -> 1.0271231
A126: solana | B126: 2026-09-06T15:10:01 | C126: 15GSKjZ7QMS3JFWUp45fCq7ySSxzLpubYo6p3dZLMkKTH9c2NpyNePJmvWPQkZdnxtPMN7Yp7nkij9b3qD5Xg1S | D126: success | E126: atomic flash arb | F126: OKX | G126: PYUSD +1.0298 | H126: 1.029764 | I126: 0.0011718403 | J126: =H126-I126 -> 1.0285922
A127: solana | B127: 2026-09-06T15:11:27 | C127: 5JkWVA6CAt6v9ZsWjdV4cFYLQYrg3tHqUgykjaTdyPXrrCdGeNoRNbDPnmHQ7ui8QzJ7LhinAfWF7hm7vZPnmKoh | D127: success | E127: atomic flash arb | F127: OKX | G127: PYUSD +1.0463 | H127: 1.046322 | I127: 0.0011810045 | J127: =H127-I127 -> 1.045141
A128: solana | B128: 2026-09-06T15:15:01 | C128: 3dM7gdg2TFjU8K1dnw1TvSPBDgmiYqKjZXAQ5vJA2rn8QXRuHTc5kwWf8wDoL1zirhM1J4kNKyzhqFUhgMVnxFY | D128: success | E128: atomic flash arb | F128: OKX | G128: PYUSD +1.3085 | H128: 1.30853 | I128: 0.0012027427 | J128: =H128-I128 -> 1.3073273
A129: solana | B129: 2026-09-06T20:34:21 | C129: 4maNhf4BjNk8qdgyb7snw3g5NHLEqL7x5xPPYtpkMPw3VGycazZGL2kKuUENgZwCWLA67EUvFGnSSCoFPboZmdpy | D129: success | E129: atomic flash arb | F129: OKX | G129: PYUSD +2.8186 | H129: 2.81864 | I129: 0.0011999722 | J129: =H129-I129 -> 2.81744
A130: solana | B130: 2026-09-06T20:40:52 | C130: mMditNhv8i5GwZdcTKJa4gmtQfKky2WAwg4iimwKDR3xkwHJC8omUEA7krFWqTTR74LSwAyT7exM57Hm5i35CEb | D130: success | E130: atomic flash arb | F130: OKX | G130: PYUSD +2.5853 | H130: 2.58531 | I130: 0.0011780208 | J130: =H130-I130 -> 2.584132
A131: solana | B131: 2026-09-06T22:44:16 | C131: 2jkoRdpkyxfCNYvmqCxExy5icHc6VKBfCDRoofQfxRodUy7xJio7ite7znEjHZxnL2txCsGAEhGgza3nbdweu24A | D131: success | E131: atomic flash arb | F131: OKX | G131: PYUSD +1.4226 | H131: 1.422631 | I131: 0.0011688566 | J131: =H131-I131 -> 1.4214621
A132: solana | B132: 2026-09-09T12:00:00 | C132: 37yEHJmzkr5ZSj9XaDEnaS8iCpxbY34BNuRqBqHuPxk2tDKHPjGnhicZ8daaLYxF4foH7DMrRh9aGiu4S4npx99m | D132: success | E132: atomic flash arb | F132: Jupiter | G132: USDC +2.1529 | H132: 2.152908 | I132: 0.0011052629 | J132: =H132-I132 -> 2.1518027
A133: solana | B133: 2026-09-09T15:49:50 | C133: 2yxfCLhdU3ksRoo6i6HBj6s2i87UK2KWfHfanUp5sc9d9aY1nXwLUvfRavrMGUqMKqZiudz9ouijCfwyto7qqeGt | D133: failed | E133: atomic flash arb | F133: OKX | H133: 0 | I133: 0.0011631407 | J133: =H133-I133 -> -0.0011631407
A134: solana | B134: 2026-09-09T16:40:21 | C134: 2oFVsYW6tB4RMDQmLDtNszXUREpNj2qggme3yis5vAPYj4Wbg7b6B9AMJGFsS8doQfuHPRw8D5TJdD6uJ9Hes4kw | D134: success | E134: atomic flash arb | F134: DFlow | G134: USDG +0.0012, PYUSD +1.1564 | H134: 1.157549 | I134: 0.001213403 | J134: =H134-I134 -> 1.1563356
A135: solana | B135: 2026-09-09T17:07:50 | C135: 5ayVC9EPii69WLpSaCKWnGSpeoVyFQv3MYJyKLYdAUXVrZbfjGyBrp5oy341yMJHWvP8vFsyHLrWRgRCLcgEWKVq | D135: success | E135: atomic flash arb | F135: DFlow | G135: PYUSD +1.3748 | H135: 1.374838 | I135: 0.0012131999 | J135: =H135-I135 -> 1.3736248
A136: solana | B136: 2026-09-09T19:02:14 | C136: 4cTFmjjwvTknD5a8LxM6AnGVqoqjN6VgRMvQatwYg6d9SHtFryseEDqyRjitDqTns6MEEWxwSueyX9BEB4Tss9JY | D136: success | E136: atomic flash arb | F136: DFlow | G136: USDG +0.0007, PYUSD +1.0722 | H136: 1.072936 | I136: 0.0012011167 | J136: =H136-I136 -> 1.0717349
A137: solana | B137: 2026-09-09T19:05:30 | C137: jtQTHusWkbZfPjBY2NFkfbvrBsvsraDLQAVygtKJiFrJnkbuCHfG1EMPnN7XnSvEboKd4LPBqLRFTS6XZoHpGHp | D137: success | E137: atomic flash arb | F137: 0x | G137: PYUSD +1.7435 | H137: 1.743514 | I137: 0.0011571498 | J137: =H137-I137 -> 1.7423569
A138: solana | B138: 2026-09-09T19:06:21 | C138: 61hwgQo6iJKNP1zRyAP2CYXPhMTJCUUMHCFivuzK24crrvVsiTFaeSwKeN8aEXKsu28vVcRB7ZPiqBv2PTq3eDXg | D138: success | E138: atomic flash arb | F138: DFlow | G138: PYUSD +1.3762 | H138: 1.376239 | I138: 0.0012336095 | J138: =H138-I138 -> 1.3750054
A139: solana | B139: 2026-09-09T19:07:22 | C139: 5J7pj6Qsn5MAfZ7qeNbWdxG3G3yxBC8Xjyt4deQ1xrqdp4PJxm1SWgCWGQgA9kNhogdW7RnJ9W8EAFN9mPmkRnFV | D139: success | E139: atomic flash arb | F139: DFlow | G139: PYUSD +1.0886 | H139: 1.088628 | I139: 0.0012385849 | J139: =H139-I139 -> 1.0873894
A140: solana | B140: 2026-09-09T19:19:35 | C140: 2wptMK6vvS8zb8Kzkzw27WKBLNySFxQ3wbjKHUEjE2SBS5nWmfjik4Ap4RXkfx8zT5hiC422g7sYqz3J251iYGuw | D140: success | E140: atomic flash arb | F140: 0x | G140: PYUSD +1.6516 | H140: 1.651566 | I140: 0.0012748347 | J140: =H140-I140 -> 1.6502912
A141: solana | B141: 2026-09-09T19:20:29 | C141: 3qJ3qSWM8gQPrSydE2MtCrFL111zv8EonsRUTg5EwCcm6nTgKmamB5FsaE2DrPT9H2nbUQFdmTVpgEo7sdqnRijk | D141: failed | E141: atomic flash arb | F141: DFlow | H141: 0 | I141: 0.0011915719 | J141: =H141-I141 -> -0.0011915719
A142: solana | B142: 2026-09-09T19:22:20 | C142: 2ibRU3Gie1z6Pca7ygM3pSpUxfmC4rRe3LDEdujZkSVspiYoFcwPPSUNENg1HG1TtANwAdHqMkNDQkSw8WMp7U1S | D142: success | E142: atomic flash arb | F142: DFlow | G142: PYUSD +1.4348 | H142: 1.434794 | I142: 0.0012069044 | J142: =H142-I142 -> 1.4335871
A143: solana | B143: 2026-09-09T19:23:15 | C143: 2tExN5SDFsSD2sN5AZKvp2QGDReePJ4SSNRtfjxodN3oMGMM8NH62PaB2jx9fZ7FGQnK6EUnQCaDSHCuE58HfHqR | D143: success | E143: atomic flash arb | F143: DFlow | G143: PYUSD +1.2073 | H143: 1.207332 | I143: 0.001198172 | J143: =H143-I143 -> 1.2061338
A144: solana | B144: 2026-09-09T19:37:44 | C144: 51m9PtySfmS51ei5P5miD26RvHeX3MtcbQKXzMBrU4qQCmhvWrmSsdUhY8UrfFw9ZUqTqE7ksFwjnACj55ETtKfj | D144: success | E144: atomic flash arb | F144: DFlow | G144: PYUSD +1.1924 | H144: 1.192412 | I144: 0.0011633438 | J144: =H144-I144 -> 1.1912487
...

Sheet SOL non-atomic legs
A1: chain | B1: time_utc | C1: tx | D1: status | E1: category | F1: provider | G1: detail | H1: stable_gain_usd | I1: fee_usd | J1: net_usd
A2: solana | B2: 2026-06-24T19:29:36 | C2: 2K1N2oGwhbAsC32gmw7YPJtM4EwoU8PsABeJ7eqkrUAbo1SWruZxjnnHxkVw4oPFg2Yvs3mR9PTTa3eCUrnoz2nJ | D2: success | E2: non-atomic leg | F2: 0x | G2: USDC -99,898.6054, USDT +100,013.6856 | H2: 115.08014 | I2: 0.27779093 | J2: =H2-I2 -> 114.80235
A3: solana | B3: 2026-06-24T19:31:08 | C3: WDRgSo5KN38QBcfQQi7WgFrCw3tvWCU495KqTfifdbTfs2FcgJqSyr9nQbJSWJusS7nf1ZcLHupqkmmL11wpivE | D3: success | E3: non-atomic leg | F3: Stable.com | G3: USDT -100,023.6846, USDC +99,923.6609 | H3: -100.02368 | I3: 0.068502392 | J3: =H3-I3 -> -100.09219
A4: solana | B4: 2026-06-24T19:31:20 | C4: 2cWK6iwUjECnsnfaNth1hfPW9DW4xWermaCDkJtgTDwPX12rudnnwAK57qT41KjBYiU1UUhEVwfdpvQTUA9LRCfv | D4: success | E4: non-atomic leg | F4: 0x | G4: USDC -99,923.6609, USDT +100,038.5505 | H4: 114.88962 | I4: 0.00040806 | J4: =H4-I4 -> 114.88921
A5: solana | B5: 2026-06-24T19:31:57 | C5: LgkWaaXtRhH1D6gnXn2KABeiMNibKek8g5CmDGDAcA3axwfq25otWknYan5uakyXzBVJga2uh9NmLDgGej4CsTr | D5: success | E5: non-atomic leg | F5: Stable.com | G5: USDT -100,038.5505, USDC +99,938.5120 | H5: -100.03855 | I5: 0.00034005 | J5: =H5-I5 -> -100.03889
A6: solana | B6: 2026-06-24T19:32:18 | C6: 3iv72iL3aBwS2pb6zT26hbswMHGL555sC14T1MXUN56W87v3cZnqh6DBPykcrSKMkhQizTyJ6PFZidvYBsUEVPV6 | D6: success | E6: non-atomic leg | F6: Jupiter | G6: USDT +100,053.2339, USDC -99,938.5120 | H6: 114.72195 | I6: 0.00040806 | J6: =H6-I6 -> 114.72154
A7: solana | B7: 2026-06-24T19:33:05 | C7: 2xcTFnkFE64BPoYx7zmUA9jrEnnBMz3nXmVjkF76SJRS1Dk83XWrmct6jX45QvPaTCwL5rvzLFUiSaY1oaBbecHP | D7: success | E7: non-atomic leg | F7: Stable.com | G7: USDT -100,053.2339, USDC +99,953.1807 | H7: -100.05323 | I7: 0.00034005 | J7: =H7-I7 -> -100.05357
A8: solana | B8: 2026-06-24T19:33:55 | C8: 3VScb7g5gpFLR8kaS5ELmYf7aj9vkvbjtNPj1gkUqp6cVCGz4usmAfh6YgX4Rb12CjpN5Jz7tDTf2waZEpZXBxaT | D8: failed | E8: non-atomic leg | F8: OKX | H8: 0 | I8: 0.00040806 | J8: =H8-I8 -> -0.00040806
A9: solana | B9: 2026-06-24T19:34:10 | C9: 2wptiPxhHbG4wNZ7V2EM6rB9WTe6wXM4WpaEMSdJJkhXv1KBPz42cy8taUdTZpPCqvDCDJRrq438HubQvk2bVhzY | D9: failed | E9: non-atomic leg | F9: DFlow | H9: 0 | I9: 0.00040806 | J9: =H9-I9 -> -0.00040806
A10: solana | B10: 2026-06-24T19:34:19 | C10: 4hiVnWVkhLLyLa2JFTmiJPRa9PjMNwgZyvpkP3BZNJn6MZBqfTDiw1Zh7ySEFtaHMVNQkbDpKkyjVdC6D4GRA5Zp | D10: success | E10: non-atomic leg | F10: DFlow | G10: USDT +100,066.5579, USDC -99,953.1807 | H10: 113.37716 | I10: 0.00040806 | J10: =H10-I10 -> 113.37675
A11: solana | B11: 2026-06-24T19:34:51 | C11: ym6h21xanbc35T2muSg3JFJYqXKiTz8cewAmbKqpVcoKvhjrmVQ1jBWk7cyrskjFGTgsQyAYGs9pQ36PeXFAuR5 | D11: success | E11: non-atomic leg | F11: Stable.com | G11: USDT -100,066.5579, USDC +99,966.4913 | H11: -100.06656 | I11: 0.00034005 | J11: =H11-I11 -> -100.0669
A12: solana | B12: 2026-06-24T19:35:10 | C12: 3piH9LXCoT4DykyUgvdPTrBnEGrL3PokHJBKsGTog7UB6Ahm3HQabfPE3FEMtppdULVyHuKGFwFAYFPL9CMQNADF | D12: success | E12: non-atomic leg | F12: DFlow | G12: USDT +100,081.2543, USDC -99,966.4913 | H12: 114.76295 | I12: 0.00040806 | J12: =H12-I12 -> 114.76255
A13: solana | B13: 2026-06-24T19:41:15 | C13: 4QxCDrBCrZbvJjNnDZFyLVeQLfKvfo4bpCASoFDkn4QcBUKaXu5DkpbCwx7W2u2wqXA8uvjHJXMfTetRUjMThEHm | D13: success | E13: non-atomic leg | F13: Stable.com | G13: USDT -100,081.2543, USDC +99,981.1730 | H13: -100.08125 | I13: 0.00034005 | J13: =H13-I13 -> -100.08159
A14: solana | B14: 2026-06-24T19:41:34 | C14: 3NBGUhXfsQPBNaPmBozWQSp7DwBuawxTv7Hx11KKYaMzksbCviPqwFFpD8xyhWZqtbeG1sUCGgPJ7DRWBVmwfDsn | D14: success | E14: non-atomic leg | F14: OKX | G14: USDT +100,097.6427, USDC -99,981.1730 | H14: 116.46968 | I14: 0.00040806 | J14: =H14-I14 -> 116.46927
A15: solana | B15: 2026-06-24T19:42:00 | C15: 29gUbsYK18niwpqcqnoA4bqnNkVTbGNW2otwqoXMB8Gs1doFik1BJPiZHtL4jmqwsQxr1EoPh8tgPdDAbejr6Xif | D15: success | E15: non-atomic leg | F15: Stable.com | G15: USDT -44,998.0000, PYUSD +44,953.0020 | H15: -44.998 | I15: 0.14944517 | J15: =H15-I15 -> -45.147445
A16: solana | B16: 2026-06-24T19:42:12 | C16: 5bsWkw9Fsdp7hEgaDT9g5ngTtu7q61fBWjB1C2e9Rh8H3iM89cDWw56fb2aiCcevaYPRonNCcx7kpa6iMohCjmzf | D16: success | E16: non-atomic leg | F16: OKX | G16: USDT +45,006.4601, PYUSD -44,953.0020 | H16: 53.458054 | I16: 0.00040806 | J16: =H16-I16 -> 53.457646
A17: solana | B17: 2026-06-26T10:42:09 | C17: 5xdagLv1Mnn4QVCyhYj8e5YgXAqqTmVo6yH9oTGcVxerR5apCBFbQuJ6tJuFXzzRVY8minSScuqZqxFiUWmaB4pT | D17: success | E17: non-atomic leg | F17: OKX | G17: USDT +100,128.7302, USDC -100,016.3119 | H17: 112.4183 | I17: 0.00043074 | J17: =H17-I17 -> 112.41787
A18: solana | B18: 2026-06-26T10:44:35 | C18: H6GfffB8rKGr74gVbL5XzszDTyYhtcNqYLa5hfTmFs5Braym5wGLeN3s1FLDMazQD2xEtHykxiCskX1rbDSP1Vh | D18: success | E18: non-atomic leg | F18: Stable.com | G18: USDT -39,998.0000, PYUSD +39,958.0020 | H18: -39.998 | I18: 0.00035895 | J18: =H18-I18 -> -39.998359
A19: solana | B19: 2026-06-26T10:45:02 | C19: 4nZeDSpWvLBqbnzn5mtRQtqKDxG9Kwf2CEr9Q5gDFxqJ4tjzJS2ax8SZNYNdpJKfNGMM8Tbvr6s9RfiSary2EK3t | D19: success | E19: non-atomic leg | F19: OKX | G19: USDT +40,007.3003, PYUSD -39,958.0020 | H19: 49.29833 | I19: 0.00043074 | J19: =H19-I19 -> 49.297899
A20: solana | B20: 2026-06-26T10:45:50 | C20: 3pMorWAF2C3TBbqU76vFEQEmEiWoqYx6KT6zf2nECE2UB3n2QrczHiACJy6mpfmSP1bbUyu7kKwCocnpFsFT8f48 | D20: success | E20: non-atomic leg | F20: Stable.com | G20: USDT -100,138.0305, USDC +100,037.8925 | H20: -100.13803 | I20: 0.00035895 | J20: =H20-I20 -> -100.13839
A21: solana | B21: 2026-06-26T10:46:06 | C21: 2F7NqRCU9toTnzChayZRjL8k9CvQUe7n43Cb4LGx7qzxPQTbjbNothmvJbtZWfyp9NX34xKHKdHvaNzg7TJPJBLe | D21: success | E21: non-atomic leg | F21: 0x | G21: USDC -100,037.8925, USDT +100,149.0123 | H21: 111.11978 | I21: 0.14683065 | J21: =H21-I21 -> 110.97295
... A31: solana | B31: 2026-06-27T05:40:10 | C31: 3BmCPHLHXbyubUk65qr6mXWDpV3Wmv7xWbRNb8Ab4A6Jgve5hipdqiRsu2nzjdYwF9wNHFPBbumj3MBMx3TUukE2 | D31: success | E31: non-atomic leg | F31: Stable.com | G31: USDG +9,990.0000, USDT -10,000.0000 | H31: -10 | I31: 0.15467499 | J31: =H31-I31 -> -10.154675
A32: solana | B32: 2026-06-27T05:40:22 | C32: 31VtnBYvy4grfg2yY2b1kG9W6eHawabEUKxgJTYEhwKQd7hv97545zr2zwtUZCAkgL7zyxi6hkb5z6bH8M7TRGKv | D32: failed | E32: non-atomic leg | F32: Jupiter | H32: 0 | I32: 0.0014078 | J32: =H32-I32 -> -0.0014078
A33: solana | B33: 2026-06-27T05:40:41 | C33: 2QWKeSQN6R2pBzfpCeFfnpafzRyG3341FDdbKu5e2eGPZEHkv38XhGibw87oA8o17Mm1hTkBpU5fsfGRSYPxkzyg | D33: failed | E33: non-atomic leg | F33: Jupiter | H33: 0 | I33: 0.00057677566 | J33: =H33-I33 -> -0.00057677566
A34: solana | B34: 2026-06-27T05:40:44 | C34: 438RT4EyKjqMJfSvn2sJDS14yu5QSKL48thnrnhBTeF8VLmdNQNkCCc3rZ1jDqug1KaFwhPPjy6YUdQVgBdhBtFg | D34: failed | E34: non-atomic leg | F34: Jupiter | H34: 0 | I34: 0.00052468706 | J34: =H34-I34 -> -0.00052468706
A35: solana | B35: 2026-06-27T05:40:48 | C35: 45A3DYGRqVHSfK8ZD5iDWAjteaqypq94FofNKkG5CHRtYmSwCa2dJFNTBiUSzixo632LaSirtVJMxfnkiqTNwvET | D35: failed | E35: non-atomic leg | F35: Jupiter | H35: 0 | I35: 0.0004336024 | J35: =H35-I35 -> -0.0004336024
A36: solana | B36: 2026-06-27T05:40:53 | C36: 5u67idb2Cu2sAc7f6KRHvkGYjwGier5bMNPgnzBRba6ZJLhKNHZidaRqUqWqSYdQyo2aEQA1b4dDV6oFbp9VT2Uw | D36: success | E36: non-atomic leg | F36: Jupiter | G36: USDT +1,000.0286, USDC -998.9132 | H36: 1.115403 | I36: 0.00098947223 | J36: =H36-I36 -> 1.1144135
A37: solana | B37: 2026-06-27T05:41:07 | C37: 36NF9UMHvNnRTdFDfSzvNkDLNgNtfFtDXuqAKz7RfuZtrGPssn1mefZwuhrr6BfePDWiUkCj9SCy1KpDpc7cRqwT | D37: success | E37: non-atomic leg | F37: Jupiter | G37: USDT +1,000.0561, USDC -998.9407 | H37: 1.115436 | I37: 0.0053960974 | J37: =H37-I37 -> 1.1100399
A38: solana | B38: 2026-06-27T05:41:34 | C38: 2k3dDFfPoyw9VExqk5Rkqaje7vu5wGrffFZqc6BrPqXgDcoHpSijSTtqcLH1GYqZYEnk6ByjZByo8hrDELCcWNdL | D38: failed | E38: non-atomic leg | F38: Jupiter | H38: 0 | I38: 0.00059022015 | J38: =H38-I38 -> -0.00059022015
A39: solana | B39: 2026-06-27T05:41:38 | C39: 2uj5M9iQ9grjRCVw37ncPPNi1vMizxyyo3Rwsew8Fcj739nEJX8exG76A2BCBLkYGDMDQ9CHneJkmgCy4HUjFqTm | D39: success | E39: non-atomic leg | F39: Jupiter | G39: USDT +1,000.0840, USDC -998.9678 | H39: 1.116198 | I39: 0.0010813312 | J39: =H39-I39 -> 1.1151167
A40: solana | B40: 2026-06-27T05:41:47 | C40: 5Md5JX9jWkXXMk1vdk2o6UchXRGjBYRjpWRrAqxGvQ2PqrJ4F6y5sez4wakqw1LTi3eYN2PhCrTrZSkfRKCVLebG | D40: failed | E40: non-atomic leg | F40: Jupiter | H40: 0 | I40: 0.00095181358 | J40: =H40-I40 -> -0.00095181358
A41: solana | B41: 2026-06-27T05:46:02 | C41: 61VtvrouLMdJY2SeL9PmN8kceiDxyaDXf8vuZdf4cDt9oDSb16mWnoUidsAmZ78A7yy5WQioKfEySawjPtD95SEr | D41: failed | E41: non-atomic leg | F41: Jupiter | H41: 0 | I41: 0.00036940672 | J41: =H41-I41 -> -0.00036940672
A42: solana | B42: 2026-06-27T05:46:03 | C42: 42UquMGmevBytFFpu51VrB4uSGSNQJiQuZEZPg9LTKLpKAq753h4Lo8wotEyExGq5yCFgyed2RdXw5uY5FLThetC | D42: failed | E42: non-atomic leg | F42: Jupiter | H42: 0 | I42: 0.00105585 | J42: =H42-I42 -> -0.00105585
A43: solana | B43: 2026-06-27T05:46:06 | C43: 5WC5HsCimFLDieANUoqp789GYXxAT5m1exCnu9oZejEmfeZSPHpK6Y67QTWe12wnTTo969sebPrzzVecrm8mnXUC | D43: success | E43: non-atomic leg | F43: Jupiter | G43: USDT +1,000.1130, USDC -998.9958 | H43: 1.117129 | I43: 0.0017576383 | J43: =H43-I43 -> 1.1153714
A44: solana | B44: 2026-06-27T05:46:13 | C44: 5JJew2XAhpi4vgAeK9itxMnjujy4PMBBVmnLwP5oDyZKS2uVvkeRnAWB29HeaG5NR6Aoqpc6aY5uhvWZt5VZdnqz | D44: success | E44: non-atomic leg | F44: Jupiter | G44: USDT +1,000.1203, USDC -999.0042 | H44: 1.116184 | I44: 0.0013501506 | J44: =H44-I44 -> 1.1148338
A45: solana | B45: 2026-06-27T05:46:30 | C45: iPTZBNu8uHCgAot5Q4K1XH8cuzeJ7rGPnrSx8VsEa8HTcLRrwuKAhFxeRNVhZB1ibYPq6aNJ614ywdGbcUn1mBc | D45: failed | E45: non-atomic leg | F45: Jupiter | H45: 0 | I45: 0.0014078 | J45: =H45-I45 -> -0.0014078
A46: solana | B46: 2026-06-27T05:46:32 | C46: 3RnWP4hMjTd4KX6aor9P5wnd4QmdjSF9zcdUqtbHxN4N3Vyqr3vxkc41EAprCFncUMM67jpYyF2445RviTTjn4tc | D46: failed | E46: non-atomic leg | F46: Jupiter | H46: 0 | I46: 0.0014078 | J46: =H46-I46 -> -0.0014078
A47: solana | B47: 2026-06-27T05:46:33 | C47: 4NuTwLN27gV1VCJC9DW65z1feUnPiGgr5LNwYehrMyxENQA34SnmdQBj6bGYhQMpxzprhHaj6gDyxdkNgFPHggCu | D47: success | E47: non-atomic leg | F47: Jupiter | G47: USDG -9,990.0000, USDT +10,001.9020 | H47: 11.901964 | I47: 0.0016396647 | J47: =H47-I47 -> 11.900324
A48: solana | B48: 2026-06-27T05:46:51 | C48: 4AUFkt72juMHaJUH1mRGhppcdUQJbK3unUD2CPJbowXceroE3mnypkjrRh7BkKiqTkysNCMnNyqvKi4qddZq2Pfs | D48: success | E48: non-atomic leg | F48: Jupiter | G48: USDT +1,000.0109, USDC -998.8902 | H48: 1.120722 | I48: 0.0012442136 | J48: =H48-I48 -> 1.1194778
A49: solana | B49: 2026-06-27T05:46:53 | C49: 5xmAnPjpYAHvG8d7KvgHUP2v8MuWVHQUN4uuLs6Nhb24Gumzh16vCL561WTAMWQ9oYH8kBwF5UqxWoi4UNPB747n | D49: success | E49: non-atomic leg | F49: Jupiter | G49: USDT -1,000.0109, USDC +998.8884 | H49: -1.122466 | I49: 0.0012990474 | J49: =H49-I49 -> -1.123765
A50: solana | B50: 2026-06-27T05:46:55 | C50: 4tgvXAFaz6ywKWvpiD8gcja23JsVycoudMx8NYvJavCSEJMPiazpRpMEMp96ks2jnoN7CXfcsQQJjzvqHGyc4UNR | D50: failed | E50: non-atomic leg | F50: Jupiter | H50: 0 | I50: 0.00057811307 | J50: =H50-I50 -> -0.00057811307
A51: solana | B51: 2026-06-27T05:47:01 | C51: 3S58ivyczK54QdGDGLgSrxL8JGZRvqMoQgzzC5igQbTrSps3Gvz3K4bzSUQwvyHztkJst879iT5pgb1MvPXqYKs | D51: success | E51: non-atomic leg | F51: Jupiter | G51: USDT +1,000.0100, USDC -998.8893 | H51: 1.12073 | I51: 0.00175975 | J51: =H51-I51 -> 1.1189703
A52: solana | B52: 2026-06-27T05:47:04 | C52: 5WVq8HwRju4axDAvzn5yPiJG2qY19uZDkWURY4ZteG4ZP2sX6YekT95zh5hkGrrogDhJvPpwjvcGDdgsEkh2pgz1 | D52: success | E52: non-atomic leg | F52: Jupiter | G52: USDT -1,000.0106, USDC +998.8873 | H52: -1.123305 | I52: 0.0011236356 | J52: =H52-I52 -> -1.1244286
A53: solana | B53: 2026-06-27T05:47:08 | C53: 5TSkL4FYghJFXUH8ae5ra8bmtZDnMxKAUwjnxXxF9eDBc2wnphXx4mH4NMSSrEcqnMvsFzCJxJtf7KnAEg8mjmNX | D53: success | E53: non-atomic leg | F53: Jupiter | G53: USDT +1,000.0089, USDC -998.8873 | H53: 1.121518 | I53: 0.00175975 | J53: =H53-I53 -> 1.1197583
A54: solana | B54: 2026-06-27T06:08:33 | C54: qqk5mjWY7DEBRvTkKKe9sY2eMthJzWXFFseNJMr155YfjyHD5A1dxNpubfHFEMBNqWGAgWFWTpwDyrQfHh56sqW | D54: success | E54: non-atomic leg | F54: Jupiter | G54: USDT +100,118.5136, USDC -100,004.3639 | H54: 114.14967 | I54: 0.14485051 | J54: =H54-I54 -> 114.00482
A55: solana | B55: 2026-06-27T06:08:54 | C55: 5XZMg8eE11fuADR5xT1eBo1kafGrLeE6kHKc8sJoNwpkjwqNXqjX3dNSGMepVW9AtEHWHyzm5wyt1yvD8E53sRT | D55: failed | E55: non-atomic leg | F55: Jupiter | H55: 0 | I55: 0.00037630494 | J55: =H55-I55 -> -0.00037630494
A56: solana | B56: 2026-06-27T06:09:02 | C56: 4cpeyHPmwfZjzbxYixW5VhvywhEKssKL6iYQB8NpYCsj5zPLCoyVdkpenztwGzZtimZBDgdcMXAGHHxeuFFAa5Lj | D56: failed | E56: non-atomic leg | F56: Jupiter | H56: 0 | I56: 0.00071804839 | J56: =H56-I56 -> -0.00071804839
A57: solana | B57: 2026-06-27T06:09:09 | C57: 2xVGfSHWt3jo4zEpibgYJwA8NtiP3Jf9FedqstRfrm6m4Ct2Mph3PNHRfLZ9ZZCt23k3oezrvAjBsaWQUzxny16u | D57: failed | E57: non-atomic leg | F57: Jupiter | H57: 0 | I57: 0.00072881806 | J57: =H57-I57 -> -0.00072881806
A58: solana | B58: 2026-06-27T06:09:11 | C58: 2YaSGVSNe7UCFUN7nBsxerDkAzLU5122Hp6whQ91ow3MKCLZgpk2dW3jQtNAS1SbzpTgPU4dnxSkhcJUqKJLVtrK | D58: success | E58: non-atomic leg | F58: Jupiter | G58: USDT +999.7663, USDC -998.6222 | H58: 1.144016 | I58: 0.0013188974 | J58: =H58-I58 -> 1.1426971
A59: solana | B59: 2026-06-27T06:09:19 | C59: 4XfcZZEKDpjC4RKNz7LhKGy5hEGbMeikrgn6vukZUQbGet8TTo4Hb6kmiNo6S17sUuG2SoSyyLxsjVgoYUn2BxZ5 | D59: failed | E59: non-atomic leg | F59: Jupiter | H59: 0 | I59: 0.00105585 | J59: =H59-I59 -> -0.00105585
A60: solana | B60: 2026-06-27T06:09:21 | C60: 3mGetfjHdcA14kQGZerk42Yw1S1NQfQLxALx5cyWoBGmAXuVPWFZxe5QPeGeBJNYVe4hhPrmEz7oZT72U5nUqwak | D60: failed | E60: non-atomic leg | F60: Jupiter | H60: 0 | I60: 0.00105585 | J60: =H60-I60 -> -0.00105585
A61: solana | B61: 2026-06-27T06:09:26 | C61: 4tLYQY6ZS72pziNWjCfB8Z9PV6NzA6KPMDzZyYtohijXwj1M3h8pJzSEyyuECS3x99ng5PpEJM74j9vuYAVRwH3b | D61: success | E61: non-atomic leg | F61: Jupiter | G61: USDT -1,000.0000, USDC +998.8527 | H61: -1.147298 | I61: 0.0021258484 | J61: =H61-I61 -> -1.1494238
A62: solana | B62: 2026-06-27T06:09:29 | C62: 3Lm8UcePuK2JJjcppPLrRVBKwriRTut4erQmrkiLHLcs1W7qfZZJ6hq5KHKgXeL5P9FWymfkiBgTv2zhrgxf3Kmu | D62: success | E62: non-atomic leg | F62: Jupiter | G62: USDT +999.9981, USDC -998.8530 | H62: 1.145124 | I62: 0.0012392863 | J62: =H62-I62 -> 1.1438847
A63: solana | B63: 2026-06-27T06:10:40 | C63: HWEchNt29CVyw6opR9eVe2BDDTqhNKCcjLCM6fmNL66JfkerfzBPwE8ikXAa2VFCXC8LZd6dUWrUiB6rnKp5GiH | D63: success | E63: non-atomic leg | F63: Stable.com | G63: USDT -100,000.0000, USDC +99,900.0000 | H63: -100 | I63: 0.0058179447 | J63: =H63-I63 -> -100.00582
A64: solana | B64: 2026-06-27T06:11:45 | C64: 3eeN6B5gjxkv5V3fCrAzJwxTBHwB5zPL9HFtXGnLLPgYs8PfiUKph3EbtJ9TfwSqLCS5YcjxCrLeYU4ak8rSUngp | D64: success | E64: non-atomic leg | F64: Jupiter | G64: USDT +100,012.9905, USDC -99,900.0008 | H64: 112.98976 | I64: 0.0026342754 | J64: =H64-I64 -> 112.98712
A65: solana | B65: 2026-06-30T04:59:17 | C65: 3RNvPPpeKCA6Gixqxh3hrbk2EirwaVMEmumkGAvmtV66N23Wx4YmKXFU3qapLmV9qqGDnVGUjic2k3NKDRhoTZon | D65: success | E65: non-atomic leg | F65: Stable.com | G65: USDT -49,998.0000, PYUSD +49,948.0020 | H65: -49.998 | I65: 0.16715561 | J65: =H65-I65 -> -50.165156
A66: solana | B66: 2026-06-30T04:59:56 | C66: 5Q4m8Q9xHWnRyKCrRFPQkGHvq9gUosMP9k5h2nkoKwGjHwmD18xb1L4WBdsPUnNbce4ivUgWdybEGmYQTpYPR7TC | D66: success | E66: non-atomic leg | F66: Jupiter | G66: USDT +50,017.0377, PYUSD -49,948.0020 | H66: 69.035743 | I66: 0.0091861743 | J66: =H66-I66 -> 69.026557
A67: solana | B67: 2026-07-08T01:24:19 | C67: 5JXqdYRHQn29WcjNjgz5fC8BruZwPyaWvQ2CoVUDhufKpmp3qECXzanCtr7ncLg76spmXARSNL4Nu2sEUPXKDNUr | D67: success | E67: non-atomic leg | F67: Stable.com | G67: USDT -49,998.0000, PYUSD +49,948.0020 | H67: -49.998 | I67: 0.0062565696 | J67: =H67-I67 -> -50.004257
A68: solana | B68: 2026-07-08T01:24:58 | C68: xDR3MfM3FCkJLU6s7Mdnt1HRjAd8cCANNJSRtUFfiZE6TtBH9DYfptZGoqcbysptc1wxitHW1giVxzNWpoFdtLK | D68: success | E68: non-atomic leg | F68: Jupiter | G68: USDT +49,983.7953, PYUSD -49,948.0020 | H68: 35.793301 | I68: 0.054248642 | J68: =H68-I68 -> 35.739052
A69: solana | B69: 2026-07-10T09:45:22 | C69: 47bDdBzNsx3fFmTaAMXvcyeXwshcswo1N9eMEFj4KwWVkYaCyATAsGn2S3knJn9aD9fjzhx8SX28k44wN91HRmCT | D69: success | E69: non-atomic leg | F69: Jupiter | G69: USDT -49,997.4724, USDC +49,972.3745 | H69: -25.097974 | I69: 0.1569207 | J69: =H69-I69 -> -25.254895
A70: solana | B70: 2026-07-10T09:47:35 | C70: 2acjj9cy1UBGxzSnZTkrrBYMLM8brzzUthBjAMG2iAg6BqQWR33aHEby59nan1AuQC2ZKAmVK31ez9snoKqFQJao | D70: success | E70: non-atomic leg | F70: Stable.com | G70: USDC -49,972.3745, PYUSD +49,972.3745 | H70: 0 | I70: 0.0061961817 | J70: =H70-I70 -> -0.0061961817
A71: solana | B71: 2026-07-10T09:47:53 | C71: 5Sz5jCP8hs2DRy8xFXKRmVUJacrwBFiVhvD2xurCrubuV2JaaeiGv7zm7yezFagCxoMSynqdJPwts3QYLwwgekuy | D71: success | E71: non-atomic leg | F71: Jupiter | G71: USDC +49,975.2674, PYUSD -49,972.3745 | H71: 2.892906 | I71: 0.013265732 | J71: =H71-I71 -> 2.8796403
A72: solana | B72: 2026-07-10T09:48:36 | C72: RVRArojhmuG5fFj2csJWLeuRf7V7MCeUeK37EQqmf2mx5fhTMc4zqm36m8hk5Zo9omKy52QL5bzMeYU9ezPvVRV | D72: success | E72: non-atomic leg | F72: Stable.com | G72: USDG +20,360.0000, USDC -20,360.0000 | H72: -3.6379788e-12 | I72: 0.17691786 | J72: =H72-I72 -> -0.17691786
... A82: solana | B82: 2026-07-10T15:02:09 | C82: x7fEaEgQteEBbqY8CQunFd368igWuuZ9KHC2tTYA3pkWF6697CVshdAds1BkEAUbwSvNLng56aNTv65FZ9w4j2L | D82: success | E82: non-atomic leg | F82: Stable.com | G82: USDC -30,000.0000, PYUSD +30,000.0000 | H82: 0 | I82: 0.0061961817 | J82: =H82-I82 -> -0.0061961817
A83: solana | B83: 2026-07-10T15:02:22 | C83: 2h6nAPKV72szoNSx3s7nRRh1p1HnW6ALsDhc7AXjZZuNgPNuMRDHdzxS2XvVtX46dvb4gYbtxRD4mBXUizSBTqhZ | D83: failed | E83: non-atomic leg | F83: Jupiter | H83: 0 | I83: 0.00117105 | J83: =H83-I83 -> -0.00117105
A84: solana | B84: 2026-07-10T15:02:26 | C84: 2EGUFDPFaUjWhEiaMW67jWQK7gDrwLCwtJnKGpGZWjsMTrUZoy3GCCwirvqK8bSFpqxBUCz7bYUPqEL51MrLREf1 | D84: failed | E84: non-atomic leg | F84: Jupiter | H84: 0 | I84: 0.00117105 | J84: =H84-I84 -> -0.00117105
A85: solana | B85: 2026-07-10T15:02:29 | C85: 2H9nCGexCgNnQGjDvaWymahPKwTd7GDVkLrwPQ4uRsk4Df5kL7HdjnPSjHjzYV2YozC7ezLRcry5ZuXryxqAmj57 | D85: failed | E85: non-atomic leg | F85: Jupiter | H85: 0 | I85: 0.00117105 | J85: =H85-I85 -> -0.00117105
A86: solana | B86: 2026-07-10T15:02:35 | C86: 3EyM1Y2kVeBXrKBhk6T5bWMqFSkYCKrLxEPRsgaQDkMaNQEEKP6Xtu91AeFPn6uNYrdK8bcM477a5M6Dfeges7Zm | D86: failed | E86: non-atomic leg | F86: Jupiter | H86: 0 | I86: 0.00117105 | J86: =H86-I86 -> -0.00117105
A87: solana | B87: 2026-07-10T15:02:42 | C87: EBjxmztiRpfJd4NhPhwuZgkgHsuZvjCuDwxf8yX9DKmM8yrKYjAmdMmDLVaAbZbKxFBRwi7XgSqaN1cYzY2uJFn | D87: success | E87: non-atomic leg | F87: Jupiter | G87: USDC +30,001.2159, PYUSD -30,000.0000 | H87: 1.215909 | I87: 0.071778885 | J87: =H87-I87 -> 1.1441301
A88: solana | B88: 2026-07-10T15:08:47 | C88: 24rZ8yh3j8fYtdhQyrU2RZfyGyy8fcirwN58StVwmGucjBQvAtH66s8qcr7HKYaZjQvdogz8WFWRbVRGhdLdYZGc | D88: success | E88: non-atomic leg | F88: Stable.com | G88: USDC -49,980.4015, PYUSD +49,980.4015 | H88: 0 | I88: 0.0061961817 | J88: =H88-I88 -> -0.0061961817
A89: solana | B89: 2026-07-10T15:09:53 | C89: 43M87EwDcp1ohU2usEVwdzuffT117vjZrMtYGPLRwhxNP4khDtPC5kS6WbEDpg2z5Qerzm4JaQsUPKQArmCnm7mc | D89: success | E89: non-atomic leg | F89: Stable.com | G89: USDG +19,998.0000, PYUSD -19,998.0000 | H89: 3.6379788e-12 | I89: 0.0061316959 | J89: =H89-I89 -> -0.0061316959
A90: solana | B90: 2026-07-10T15:11:22 | C90: 22Uc4FWSpAHzgm3G5FUpdX4YSEPyHP9afZ5cykY5qsjqrwb1GzT2Z6HkbAdQjLsS1HyRehBDPqGaEfxdTntvZhgi | D90: success | E90: non-atomic leg | F90: Jupiter | G90: USDG -19,998.0000, USDC +20,001.5806 | H90: 3.580583 | I90: 0.0017547013 | J90: =H90-I90 -> 3.5788283
A91: solana | B91: 2026-07-10T15:21:38 | C91: 3MFNnh1LbMqrtJm8ZLm4rf9Fm1ReDDQtFBtGh7TZuHGHk3xErPwMyW5cmrEuyPE9Bhzv2LYug3XMNXubxcf1HYPw | D91: success | E91: non-atomic leg | F91: Stable.com | G91: USDG +19,998.0000, PYUSD -19,998.0000 | H91: 0 | I91: 0.0061316959 | J91: =H91-I91 -> -0.0061316959
A92: solana | B92: 2026-07-10T15:21:57 | C92: 5eMJJMVwL6SNK1xTk6o2JxQMU3KA61ptBUCtmUEwzou7HbwBetybkUcTMpDcrHC4kNS6q3geLL7qL9qmRuPTVNL7 | D92: success | E92: non-atomic leg | F92: Jupiter | G92: USDG -19,998.0000, USDC +19,998.9894 | H92: 0.989351 | I92: 0.00195175 | J92: =H92-I92 -> 0.98739925
A93: solana | B93: 2026-07-10T16:15:47 | C93: 26js5t9DWSnrpLBifeYuxpEVQTrFJYC9Kj2xJEaz2kdcYLNBrkJUEpS3ifcirgDqn42ytCJoMR6bz5LT51Ckm8H1 | D93: success | E93: non-atomic leg | F93: Stable.com | G93: USDG +1,000.0000, USDC -1,000.0000 | H93: 0 | I93: 0.00195175 | J93: =H93-I93 -> -0.00195175
A94: solana | B94: 2026-07-10T16:17:54 | C94: 4etYqDtayZcKXfprEgWbSLn4NQ2MkotKZWbf2Lrj7DbtbS7wQT7368WopNgy5hRcygUVLPHkBBPv4DuxW83T3Bhb | D94: success | E94: non-atomic leg | F94: Stable.com | G94: USDG +1,000.0000, USDC -1,000.0000 | H94: 0 | I94: 0.00195175 | J94: =H94-I94 -> -0.00195175
A95: solana | B95: 2026-07-10T16:22:52 | C95: 4QyF1Fp4QxrHhpkdtozvzdoF6C8womhDQJrBpE1YGVXnJ7D1JetfWrSwXSCwXhTMPhjwx69zywuNYJfyxX7N6jL1 | D95: success | E95: non-atomic leg | F95: Stable.com | G95: USDG +17,998.0000, USDC -17,998.0000 | H95: 0 | I95: 0.00195175 | J95: =H95-I95 -> -0.00195175
A96: solana | B96: 2026-07-10T16:23:03 | C96: 4T4SkviqGsnvFR7z8HrQLTFfLgxMvXvTrVdDeRQTa7PYV4JRjqn28sMQ5QzHHXA4exvRWCCFmrZEDqjbCZxkeNfT | D96: success | E96: non-atomic leg | F96: Jupiter | G96: USDG -19,998.0000, USDC +19,999.3724 | H96: 1.372447 | I96: 0.00195175 | J96: =H96-I96 -> 1.3704953
A97: solana | B97: 2026-07-10T16:33:48 | C97: 4XTeB6YNbTWzsgjm11je52tLWZJXbxR7nxkdr6CqKZgoGQ8fjHCHYaFQqsd3GNi9stHJsnm2d6Lq34UCy8vCSxSq | D97: success | E97: non-atomic leg | F97: Stable.com | G97: USDG +19,998.0000, USDC -19,998.0000 | H97: 0 | I97: 0.00195175 | J97: =H97-I97 -> -0.00195175
A98: solana | B98: 2026-07-10T16:33:56 | C98: 4FKa2n6xhhFZQ1oWNCSujVJvsRjP1JZVBckMVXJBYSqsw1FtN73mD5NEFZrKMVddeQEoEgUHgqj6nHPp2JpT5hPC | D98: failed | E98: non-atomic leg | F98: Jupiter | H98: 0 | I98: 0.00117105 | J98: =H98-I98 -> -0.00117105
A99: solana | B99: 2026-07-10T16:34:02 | C99: 5aFHs4zMbTPCKF9L1B7h7yzWHaKWieGwxwxkYUKhkEXB4GN45tLdqxoSHdLTzC2J6KtffT9p9x4zVELhKFXQ99Xk | D99: success | E99: non-atomic leg | F99: Jupiter | G99: USDG -19,998.0000, USDC +19,998.6847 | H99: 0.684689 | I99: 0.00195175 | J99: =H99-I99 -> 0.68273725
A100: solana | B100: 2026-07-10T16:54:04 | C100: 4GyEWxPhHB5fc3EkBjTQdgSx848vmC3dJnByBAm9URnUBM1FUFtZ1EMuMYgYoL6vmq3AbuRFUdMgmp12bjEHc4oQ | D100: success | E100: non-atomic leg | F100: Stable.com | G100: USDG +19,998.0000, USDC -19,998.0000 | H100: -3.6379788e-12 | I100: 0.00070263 | J100: =H100-I100 -> -0.00070263
A101: solana | B101: 2026-07-10T16:57:01 | C101: 5Jr6Sm83Y5aCdsFHZTsrpnL17G3LrKknsxh6NCrYdoxzwSchLgaJWRCo8sJya5roiS78wY7oiY8WChsrhm1JcjjS | D101: success | E101: non-atomic leg | F101: Jupiter | G101: USDG -19,998.0000, USDC +19,998.9687 | H101: 0.968746 | I101: 0.00117105 | J101: =H101-I101 -> 0.96757495
A102: solana | B102: 2026-07-10T16:59:03 | C102: 3HCgEnvujkwu3R6W2sUbKWNcmoyF4cg2WeNg6vRwh6Ye8FKTMcHFcQge3cbWjFVUvxhsZQenELVxDRRGv6RSEqgV | D102: success | E102: non-atomic leg | F102: Stable.com | G102: USDG +19,998.0000, USDC -19,998.0000 | H102: 0 | I102: 0.00070263 | J102: =H102-I102 -> -0.00070263
A103: solana | B103: 2026-07-10T16:59:06 | C103: 4kmUCpiSM9L61JG5fw3ju9S6ERKbN8JkRSzhrvYLzfRdmttD3k96uZ5UXWYVfESw6zBsPy5brDNdoztXosmXT6Fs | D103: success | E103: non-atomic leg | F103: Jupiter | G103: USDG -19,998.0000, USDC +19,998.7309 | H103: 0.730894 | I103: 0.00117105 | J103: =H103-I103 -> 0.72972295
A104: solana | B104: 2026-07-10T17:02:17 | C104: 2FxjdfwDRrSKyiChguQxEHUrP6gqVqvv2bZzDvJi11nqfdgPhR1fFTNHQHtU26nQwXcNGoBgBHYXYUvCp5NzLwhz | D104: success | E104: non-atomic leg | F104: Jupiter | G104: USDC -40,004.3267, PYUSD +40,004.8268 | H104: 0.50006 | I104: 0.00080037364 | J104: =H104-I104 -> 0.49925963
A105: solana | B105: 2026-07-10T17:03:25 | C105: 2t2kkRv8HCFyFEZzfpQMXkLSxpySK8V6GQJsnj2FJgSuGP1pMLDtAedeNsRgUtB6WmczJ16LEPpzERYi3QPxMEEu | D105: success | E105: non-atomic leg | F105: Stable.com | G105: USDC +49,989.0000, PYUSD -49,989.0000 | H105: 0 | I105: 0.00070263 | J105: =H105-I105 -> -0.00070263
A106: solana | B106: 2026-07-10T17:03:27 | C106: 5jRZKgFTyg6JwR6qw1YcQjvYnQcTLTYUFKMF964JEB5YkWvEGdRYo85j6eF8ttJgR6iy1cxkAVUvZoS6qD9NMD57 | D106: success | E106: non-atomic leg | F106: Jupiter | G106: USDC -49,989.0000, PYUSD +49,989.3880 | H106: 0.387955 | I106: 0.00117105 | J106: =H106-I106 -> 0.38678395
A107: solana | B107: 2026-07-10T17:04:31 | C107: 4mA4MRG6DrZ1oiWDmj8pwDcEqDBWuRK2De3ZLCTn4Wc6vL79HwAsN9yqPA6F4GT1LXyWa8cYuGHM5Ai28fm5PLYh | D107: success | E107: non-atomic leg | F107: Stable.com | G107: USDC +49,989.0000, PYUSD -49,989.0000 | H107: 0 | I107: 0.00070263 | J107: =H107-I107 -> -0.00070263
A108: solana | B108: 2026-07-10T17:04:34 | C108: 4Tctq7x5BM8PcFX8H4G4HDm1dMamvTYMcxzL9o8QBUC2kVyJewNjfScQXXXHYwLHZSAWEwnakQTRqTCtGUrDRgYf | D108: success | E108: non-atomic leg | F108: Jupiter | G108: USDC -49,989.0000, PYUSD +49,989.1073 | H108: 0.107293 | I108: 0.00095620136 | J108: =H108-I108 -> 0.1063368
A109: solana | B109: 2026-07-10T17:06:08 | C109: 3CjBhz5JKn5Fq1pqGiZYkTRVCqKSjwYLpmTYSUbzRWNzJ9cdkz1nYPNSw8NxJLuXSiYq7VkgBHjbXMcD1EW3ACaU | D109: success | E109: non-atomic leg | F109: Stable.com | G109: USDC +49,989.0000, PYUSD -49,989.0000 | H109: 0 | I109: 0.00070263 | J109: =H109-I109 -> -0.00070263
A110: solana | B110: 2026-07-10T17:08:37 | C110: 4E1Z52nds2ECK9QuqbXy2uZwTJR4JzogkGpTHapxJFKAH9QqwC2PvtZX5k98uecRq32pbVu87wPgdgB2ykhR4sB7 | D110: success | E110: non-atomic leg | F110: Stable.com | G110: USDC -49,989.0000, PYUSD +49,989.0000 | H110: 0 | I110: 0.00070263 | J110: =H110-I110 -> -0.00070263
... A118: solana | B118: 2026-07-10T17:32:43 | C118: 5P1JUURPJn7EbgxCV2ZRyAVdZ5dsUSeJwLKvDw9jArZwDsqDJYweJScZYRaXiokVPPGnnCjzst7FuRGBmo57bLS4 | D118: success | E118: non-atomic leg | F118: Stable.com | G118: USDG +19,998.0000, USDC -19,998.0000 | H118: -3.6379788e-12 | I118: 0.00070263 | J118: =H118-I118 -> -0.00070263
A119: solana | B119: 2026-07-10T17:32:45 | C119: 3jUVSYpREhs8qHtVmpnRewTUVXKBecPDR3eUPxPZYuFbqK3tRKEeHPcHjhWsVppURsGqSZUCDz55bNM474E7C8K2 | D119: failed | E119: non-atomic leg | F119: Jupiter | H119: 0 | I119: 0.00117105 | J119: =H119-I119 -> -0.00117105
A120: solana | B120: 2026-07-10T17:33:36 | C120: 4snjytzukJNSNZbcqtt84m4fRbWsFan5zHG52hB68dHGHgxJ1kAiV35Z6cHMsyZkhNwTwaWew6AVuBbhuS3ad5Uh | D120: success | E120: non-atomic leg | F120: Jupiter | G120: USDG -19,998.0000, USDC +19,998.5560 | H120: 0.556015 | I120: 0.0018308976 | J120: =H120-I120 -> 0.5541841
A121: solana | B121: 2026-07-10T17:43:10 | C121: 4bmfwRT195BFPgvQs7KvHrAdXfNPeLopncYjZwe5M8oUmKPjqdWYB62odJRGLoFsPpPotLwoPL1DEgfUmZSjhU8m | D121: success | E121: non-atomic leg | F121: Stable.com | G121: USDG +19,998.0000, USDC -19,998.0000 | H121: 0 | I121: 0.00070263 | J121: =H121-I121 -> -0.00070263
A122: solana | B122: 2026-07-10T17:43:12 | C122: 3HMh6cPuVrPjiAK9ZHuZKmdvdSmYSqarJCF8ncrnm6Q9Gz5kStmoDoqeuQv93faknCtcvtadPkEWWoPBYwBgh725 | D122: success | E122: non-atomic leg | F122: Jupiter | G122: USDG -19,998.0000, USDC +19,998.8776 | H122: 0.877642 | I122: 0.00117105 | J122: =H122-I122 -> 0.87647095
A123: solana | B123: 2026-07-10T17:45:35 | C123: xoGrPNPTpJXRN5enQiADeohskwAUAsbtDpdU4F5cnooqits4RnWaWiKXpRTLZmfhYkNyikJGuWsEg4Q61SxoWFD | D123: success | E123: non-atomic leg | F123: Stable.com | G123: USDC -49,993.0000, PYUSD +49,993.0000 | H123: 0 | I123: 0.00070263 | J123: =H123-I123 -> -0.00070263
A124: solana | B124: 2026-07-10T17:49:35 | C124: 2a5yakr84cKipqjVF64Y4bsxvMENnFgfaEsiQqB9wWFEafoZRTHjBmBayyCe7whKYtkmeDYKCrZKV5pYTTbnBnxU | D124: success | E124: non-atomic leg | F124: Jupiter | G124: USDC +49,995.9345, PYUSD -49,993.0000 | H124: 2.934491 | I124: 0.0019158378 | J124: =H124-I124 -> 2.9325752
A125: solana | B125: 2026-07-10T17:49:46 | C125: 3gkyBpVopSGdQazPLNohdRc4eDqB2wTzgU3pndmXJNATtLwT3ZkASQ6DmStECh7A43mRu1xZ2m4X9WCbZ5iajc4i | D125: success | E125: non-atomic leg | F125: Stable.com | G125: USDC -10,015.0000, PYUSD +10,015.0000 | H125: 0 | I125: 0.00070263 | J125: =H125-I125 -> -0.00070263
...
